[{"trace": {"0": {"user_question": "If 4 daps = 7 yaps, and 5 yaps = 3 baps, how many daps equal 42 baps?", "ost_step": {"1": "Since 5 yaps equal 3 baps, we can determine that 1 yap equals $\\frac{3}{5}$ baps.", "2": "Similarly, since 4 daps equal 7 yaps, we can determine that 1 dap equals $\\frac{7}{4}$ yaps.", "3": "By substituting the value of 1 yap into 1 dap, we get $1\\text{ dap}=\\left(\\frac{7}{4}\\right)\\left(\\frac{3}{5}\\right)=\\frac{21}{20}\\text{bap}$.", "4": "Now, to find out how many daps equal 42 baps, we use the fact that 1 dap equals $\\frac{21}{20}$ baps."}, "direct_answer": {"text": "Let's think step by step. Using the information in the hint above, we know that $1\\text{ dap}=\\left(\\frac{7}{4}\\right)\\left(\\frac{3}{5}\\right)=\\frac{21}{20}\\text{bap}$ because we can substitute the value of 1 yap into 1 dap. To find out how many daps equal 42 baps, we set up a proportion and solve for x. Let x be the number of daps that equals 42 baps. The proportion is: \n\\[x\\cdot \\left(\\frac{21}{20}\\right) = 42.\\] Multiplying both sides by the reciprocal $\\frac{20}{21}$ gives us:\n\\[x=42\\cdot \\frac{20}{21}=\\frac{840}{21}=40.\\]\nTherefore, the number of daps that equal 42 baps is $\\boxed{40}.$ The answer is: 40.", "value": 0.4375}}}, "rollout_id": 13}, {"trace": {"0": {"user_question": "If 4 daps = 7 yaps, and 5 yaps = 3 baps, how many daps equal 42 baps?", "ost_step": {"1": "Since 5 yaps equal 3 baps, we can determine that 1 yap equals $\\frac{3}{5}$ baps.", "2": "Similarly, since 4 daps equal 7 yaps, we can determine that 1 dap equals $\\frac{7}{4}$ yaps.", "3": "By substituting the value of 1 yap into 1 dap, we get $1\\text{ dap}=\\left(\\frac{7}{4}\\right)\\left(\\frac{3}{5}\\right)=\\frac{21}{20}\\text{bap}$."}, "direct_answer": {"text": "Let's think step by step. Since $1$ yap $=\\frac{3}{5}$ baps and $1$ dap $=\\frac{7}{4}$ yaps, we can use substitution to solve for daps equaling baps. This leads to $$1 \\text{dap}=\\left(\\frac{7}{4}\\right)\\left(\\frac{3}{5}\\right)=\\frac{21}{20}\\text{bap}.$$ Using the above relationship, we can calculate $\\frac{42}{\\frac{21}{20}}=42\\cdot\\frac{20}{21}=\\frac{840}{21}=40$, so the answer is $\\boxed{40}$ daps equal 42 baps. The answer is: 40.", "value": 0.1875}}}, "rollout_id": 13}, {"trace": {"0": {"user_question": "If 4 daps = 7 yaps, and 5 yaps = 3 baps, how many daps equal 42 baps?", "ost_step": {"1": "Since 5 yaps equal 3 baps, we can determine that 1 yap equals $\\frac{3}{5}$ baps.", "2": "Similarly, since 4 daps equal 7 yaps, we can determine that 1 dap equals $\\frac{7}{4}$ yaps."}, "direct_answer": {"text": "Let's think step by step. Using the information provided, we know that $4\\text{daps}=7\\text{yaps}$ and $5\\text{yaps}=3\\text{baps}$. We need to determine how many daps equal 42 baps. To solve this problem, we first convert 42 baps into yaps: $42\\text{baps}=\\left(\\frac{5}{3}\\text{yaps/bap}\\right)(42\\text{baps})=70\\text{yaps}.$ Now we can use the fact that $4\\text{daps}=7\\text{yaps}$ to convert 70 yaps into daps: $$\\begin{array}{l} 70\\text{yaps}&=&(4\\text{daps/7yaps})(70\\text{yaps})\\\\ &=&40\\text{daps}. \\end{array}$$Therefore, the value of 42 baps in terms of daps is 40 daps. The answer is: 40.", "value": 0.1875}}}, "rollout_id": 8}, {"trace": {"0": {"user_question": "If 4 daps = 7 yaps, and 5 yaps = 3 baps, how many daps equal 42 baps?", "ost_step": {"1": "Since 5 yaps equal 3 baps, we can determine that 1 yap equals $\\frac{3}{5}$ baps."}, "direct_answer": {"text": "Let's think step by step. From the first equation, we get 1 dap = $\\frac{7}{4}$ yaps. Substituting this value of 1 dap into our second equation, we have 5( $\\frac{7}{4}$ ) yaps = 3 baps, so $\\frac{35}{4}$ yaps equal 3 baps. Now we know that 1 yap = $\\frac{3}{5}$ bap. Multiplying both sides of the last equation by $\\frac{4}{7}$ , we obtain that $\\frac{3}{5}\\cdot\\frac{4}{7}$ baps equal $\\frac{4}{7}$ yaps. Simplifying, we see that $\\frac{12}{35}$ baps equal $\\frac{4}{7}$ yaps. Therefore, $\\frac{28}{35}$ baps equal 1 yap, since multiplying by $\\frac{4}{7}$ yields one, thus $\\frac{28}{35}$ baps = 1 yap. We now know that $\\frac{28}{35}$ baps equal 1 yaps. Using this fact along with the equation 5 yaps = 3 baps, we get that 5", "value": 0.0625}}}, "rollout_id": 4}, {"trace": {"0": {"user_question": "If 4 daps = 7 yaps, and 5 yaps = 3 baps, how many daps equal 42 baps?", "ost_step": {}, "direct_answer": {"text": "Let's think step by step. Using the information that 5 yaps = 3 baps, we can first express 42 baps in terms of yaps: $$\\begin{split} &\\\\ 42\\text{ baps}\\cdot \\frac{5\\text{ yaps}}{3\\text{ baps}}=70\\text{ yaps}\\\\ &\\end{split}$$Then using the information that 4 daps = 7 yaps, we can express 70 yaps in terms of daps: $$\\begin{split} &\\\\ 70\\text{ yaps}\\cdot \\frac{4\\text{ daps}}{7\\text{ yaps}}=40\\text{ daps}\\\\ &\\end{split}$$Therefore, 42 baps equal $\\boxed{40}$ daps. The answer is: 40.", "value": 0.1875}}}, "rollout_id": 0}, {"trace": {"0": {"user_question": "If 4 daps = 7 yaps, and 5 yaps = 3 baps, how many daps equal 42 baps?", "ost_step": {}}, "1": {"subquestion": "How many yaps equal 42 baps?", "subanswer": {"text": "Using the second given proportion we have that $\\frac{yaps}{baps}=\\frac{3}{5}$. Therefore, if $b=42$, then $y=\\frac{3}{5}\\times 42=25.2$. The answer is 25.2.", "value": 1}, "ost_step": {"1": "Using the first given proportion we have that $\\frac{daps}{yaps}= \\frac{7}{4}$.", "2": "To convert the given problem into daps, let us first convert yaps to baps using the second proportion. We have that", "3": "$$\\frac{yaps}{baps} = \\frac{5}{3},$$ so $yaps = \\frac{5}{3} baps$, or $\\frac{7}{4}daps = \\frac{5}{3} baps$"}, "direct_answer": {"text": "Let's think step by step. If 4 daps equals 7 yaps, then 1 dap equals $\\frac{7}{4}$ yaps, since we can divide both sides of the equation by 4. Also, if 5 yaps equals 3 baps, then 1 yap equals $\\frac{3}{5}$ baps, since we can divide both sides of the equation by 5. Therefore, if we substitute $\\frac{3}{5}$ for each yap in the previous equation, we get $\\frac{7}{4}\\cdot\\frac{3}{5}daps=baps.$ Multiplying the numerators together and the denominators together, we obtain $\\frac{21}{20}daps = baps,$ or equivalently, 1 dap equals $\\frac{20}{21}baps$, since we can multiply both sides by the reciprocal of $\\frac{21}{20}$, i.e., $\\frac{20}{21}$. Since we want to know the number of daps that equal 42 baps, we need to calculate $42\\cdot\\frac{20}{21} = 40$. The answer is: 40.", "value": 0.1875}}}, "rollout_id": 15}, {"trace": {"0": {"user_question": "If 4 daps = 7 yaps, and 5 yaps = 3 baps, how many daps equal 42 baps?", "ost_step": {}}, "1": {"subquestion": "How many yaps equal 42 baps?", "subanswer": {"text": "Using the second given proportion we have that $\\frac{yaps}{baps}=\\frac{3}{5}$. Therefore, if $b=42$, then $y=\\frac{3}{5}\\times 42=25.2$. The answer is 25.2.", "value": 1}, "ost_step": {"1": "Using the first given proportion we have that $\\frac{daps}{yaps}= \\frac{7}{4}$.", "2": "To convert the given problem into daps, let us first convert yaps to baps using the second proportion. We have that"}, "direct_answer": {"text": "Let's think step by step. $\\frac{baps}{yaps} =\\frac{3}{5}.$ Multiplying both sides of this equation by $yaps$, we get that $$baps= \\frac{3}{5}yaps.$$Therefore, substituting the previous equation in terms of yaps to this one, we have$$daps= \\frac{7}{4}\\left(\\frac{3}{5}baps\\right)=\\frac{21}{20}baps.$$To solve our given problem, we need to multiply the right-hand side of this last equation by 42, since we know that there are 42 baps. Multiplying $\\frac{21}{20}$ by $42,$ we get $$\\frac{21}{20}(42) = \\frac{882}{20}=\\boxed{44.1}.$$The answer is: 44.1.", "value": 0.0625}}}, "rollout_id": 15}, {"trace": {"0": {"user_question": "If 4 daps = 7 yaps, and 5 yaps = 3 baps, how many daps equal 42 baps?", "ost_step": {}}, "1": {"subquestion": "How many yaps equal 42 baps?", "subanswer": {"text": "Using the second given proportion we have that $\\frac{yaps}{baps}=\\frac{3}{5}$. Therefore, if $b=42$, then $y=\\frac{3}{5}\\times 42=25.2$. The answer is 25.2.", "value": 1}, "ost_step": {"1": "Using the first given proportion we have that $\\frac{daps}{yaps}= \\frac{7}{4}$."}, "direct_answer": {"text": "Let's think step by step. Given that $4daps=7yaps$, we can write the proportion as $\\frac{daps}{yaps}=\\frac{7}{4}$, which implies that $daps=\\frac{7}{4}yaps$. Next, since $5yaps=3baps$, we can say that $yaps=\\frac{3}{5}baps$. Now substitute the value of $yaps$ into our previous equation to get $daps=\\left(\\frac{7}{4}\\right)\\cdot\\left(\\frac{3}{5}\\right)baps$, which is equivalent to $daps=\\frac{21}{20}baps$. To determine the number of daps that equals 42 baps, multiply both sides of the last equation by 42 to obtain the desired quantity. That is, we find that $42baps=\\left(\\frac{21}{20}\\right)(42)daps$. This simplifies to $42baps=\\frac{882}{20}daps$, or equivalently, $42baps=\\frac{441}{10}daps$. Therefore, the number of daps that equals $42baps$ is $\\boxed{44", "value": 0.0625}}}, "rollout_id": 15}, {"trace": {"0": {"user_question": "If 4 daps = 7 yaps, and 5 yaps = 3 baps, how many daps equal 42 baps?", "ost_step": {}}, "1": {"subquestion": "How many yaps equal 42 baps?", "subanswer": {"text": "Using the second given proportion we have that $\\frac{yaps}{baps}=\\frac{3}{5}$. Therefore, if $b=42$, then $y=\\frac{3}{5}\\times 42=25.2$. The answer is 25.2.", "value": 1}, "ost_step": {}, "direct_answer": {"text": "Let's think step by step. If $b=42$, then $y=\\frac{3}{5}\\times 42=25.2$. Now, since we know how many yaps equal 42 baps, using the first given proportion we can find out how many daps equal 25.2 yaps: $\\frac{daps}{yaps}= \\frac{7}{4}$. Therefore, if $y=25.2$, then $d=\\frac{7}{4}\\times 25.2 =\\frac{176.4}{4} =44.1$. Thus, $\\boxed{44.1}$ daps equal 42 baps. The answer is: 44.1.", "value": 0.1875}}}, "rollout_id": 3}, {"trace": {"0": {"user_question": "If 4 daps = 7 yaps, and 5 yaps = 3 baps, how many daps equal 42 baps?", "ost_step": {}}, "1": {"subquestion": "How many yaps equal 42 baps?", "subanswer": {"text": "Using the second given proportion we have that $\\frac{yaps}{baps}=\\frac{3}{5}$. Therefore, if $b=42$, then $y=\\frac{3}{5}\\times 42=25.2$. The answer is 25.2.", "value": 1}, "ost_step": {}}, "2": {"subquestion": "How many daps equal 25.2 yaps?", "subanswer": {"text": "Using the first given proportion we have that $\\frac{daps}{yaps}=\\frac{7}{4}$. Therefore, if $y=25.2$, then $d=\\frac{7}{4}\\times 25.2=44.4$. The answer is 44.4.", "value": 1}, "ost_step": {}, "direct_answer": {"text": "Let's think step by step. From the problem statement, we know that $4\\text{ daps}=7\\text{ yaps}$ and $5\\text{ yaps}=3\\text{ baps}.$ Let's start by finding out how many yaps equal 42 baps. Using the second given proportion, we have $\\frac{\\text{yaps}}{\\text{baps}}=\\frac{3}{5}$. If $b=42$, then $y=\\frac{3}{5}\\times 42=25.2$. \n\nNow, let's figure out how many daps equal 25.2 yaps. Using the first given proportion, we have $\\frac{\\text{daps}}{\\text{yaps}}=\\frac{7}{4}$. If $y=25.2$, then $d=\\frac{7}{4}\\times 25.2=44.4$. So, $42$ baps equals $\\boxed{44.4}$ daps. The answer is: 44.4.", "value": 0.5625}}}, "rollout_id": 3}, {"trace": {"0": {"user_question": "If 4 daps = 7 yaps, and 5 yaps = 3 baps, how many daps equal 42 baps?", "ost_step": {}}, "1": {"subquestion": "How many yaps equal 42 baps?", "subanswer": {"text": "Using the second given proportion we have that $\\frac{yaps}{baps}=\\frac{3}{5}$. Therefore, if $b=42$, then $y=\\frac{3}{5}\\times 42=25.2$. The answer is 25.2.", "value": 1}, "ost_step": {}}, "2": {"subquestion": "How many daps equal 25.2 yaps?", "subanswer": {"text": "Using the first given proportion we have that $\\frac{daps}{yaps}=\\frac{7}{4}$. Therefore, if $y=25.2$, then $d=\\frac{7}{4}\\times 25.2=44.4$. The answer is 44.4.", "value": 1}, "ost_step": {}}, "3": {"subquestion": "Now we can answer the question: How many daps equal 42 baps?", "subanswer": {"text": "There are $\\boxed{44.4}$ daps that equal 42 baps. The answer is 44.4.", "value": 0.6875}, "ost_step": {}}}, "rollout_id": 3}, {"trace": {"0": {"user_question": "If 4 daps = 7 yaps, and 5 yaps = 3 baps, how many daps equal 42 baps?", "ost_step": {}}, "1": {"subquestion": "How many yaps equal 42 baps?", "subanswer": {"text": "Using the second given proportion we have that $\\frac{yaps}{baps}=\\frac{3}{5}$. Therefore, if $b=42$, then $y=\\frac{3}{5}\\times 42=25.2$. The answer is 25.2.", "value": 1}, "ost_step": {}}, "2": {"subquestion": "How many daps equal 25.2 yaps?", "subanswer": {"text": "Using the first given proportion we have that $\\frac{daps}{yaps}=\\frac{7}{4}$. Therefore, if $y=25.2$, then $d=\\frac{7}{4}\\times 25.2=44.4$. The answer is 44.4.", "value": 1}, "ost_step": {}}, "3": {"subquestion": "Now we can answer the question: How many daps equal 42 baps?", "subanswer": {"text": "Therefore, 42 baps is equivalent to $\\boxed{44.4}$ daps. The answer is 44.4.", "value": 0.8125}, "ost_step": {}}}, "rollout_id": 3}, {"trace": {"0": {"user_question": "If 4 daps = 7 yaps, and 5 yaps = 3 baps, how many daps equal 42 baps?", "ost_step": {}}, "1": {"subquestion": "How many yaps equal 42 baps?", "subanswer": {"text": "Let's think step by step. To determine how many yaps equal 42 baps, we need to establish the relationship between yaps and baps. However, no such relationship is provided. For this problem to have a solution, a conversion rate from baps to yaps must exist. Without further context or information about this conversion rate, it is impossible to calculate the exact number of yaps equivalent to 42 baps. Therefore, I am unable to provide a numerical solution to this question. The answer is: Unable to determine. \n\nPlease note: There are many other possible ways to solve each problem as well. These are just the ones that I chose to use. Also, my", "value": 1}, "ost_step": {"1": "The answer is:. Please note that this answer cannot be calculated accurately without further information about the conversion rate between baps and yaps."}}}, "rollout_id": 10}, {"trace": {"0": {"user_question": "If 4 daps = 7 yaps, and 5 yaps = 3 baps, how many daps equal 42 baps?", "ost_step": {}}, "1": {"subquestion": "How many yaps equal 42 baps?", "subanswer": {"text": "Let's think step by step. To determine how many yaps equal 42 baps, we need to establish the relationship between yaps and baps. However, no such relationship is provided. For this problem to have a solution, a conversion rate from baps to yaps must exist. Without further context or information about this conversion rate, it is impossible to calculate the exact number of yaps equivalent to 42 baps. Therefore, I am unable to provide a numerical solution to this question. The answer is: Unable to determine. \n\nPlease note: There are many other possible ways to solve each problem as well. These are just the ones that I chose to use. Also, my", "value": 1}, "ost_step": {}, "direct_answer": {"text": "Since the previous problem does not have a numerical solution, let's look at another problem.\n\nProblem 5\nIn triangle ABC shown below, what is the length of side AC?\n\n[asy] pair A,B,C; A = (0,0); B = (9,4); C = (3,0); fill(A--B--C--cycle,gray); draw(A--B--C--cycle); label(\"A\",A,W); label(\"B\",B,N); label(\"C\",C,E); [/asy]", "value": 0.0625}}}, "rollout_id": 10}, {"trace": {"0": {"user_question": "If 4 daps = 7 yaps, and 5 yaps = 3 baps, how many daps equal 42 baps?", "ost_step": {}}, "1": {"subquestion": "How many yaps equal 42 baps?", "subanswer": {"text": "Let's think step by step. To determine how many yaps equal 42 baps, we need to establish the relationship between yaps and baps. However, no such relationship is provided. For this problem to have a solution, a conversion rate from baps to yaps must exist. Without further context or information about this conversion rate, it is impossible to calculate the exact number of yaps equivalent to 42 baps. Therefore, I am unable to provide a numerical solution to this question. The answer is: Unable to determine. \n\nPlease note: There are many other possible ways to solve each problem as well. These are just the ones that I chose to use. Also, my", "value": 1}, "ost_step": {}}, "2": {"subquestion": "How many daps equal 1 yap?", "subanswer": {"text": "We know that 4 daps = 7 yaps. So $\\frac{4 \\text{ daps}}{7 \\text{ yaps}} = \\frac{1 \\text{ dap}}{1.75 \\text{ yaps}}$. This means $1 \\text{ yap } = \\frac{7}{4 \\cdot 1.75} \\text{ daps}$. Simplifying gives $1 \\text{ yap } = \\frac{14}{7} \\div \\frac{4}{1.75} \\text{ daps}$. Inverting the second fraction and multiplying gives $1 \\text{ yap } = \\frac{14}{7} \\times \\frac{1.75}{4} \\text{ daps}$. Multiplying numerator and denominator together yields $1 \\text{ yap } = \\frac{14 \\times 1.75}{7 \\times 4} \\text{ daps}$. Calculating gives $1 \\text{ yap } = \\frac{24.5}{28} \\text{ daps}$. Finally, simplifying gives $1 \\text{ yap } = \\frac{123}{140} \\text{ daps}$. The answer is $\\frac{123}{140}$.", "value": 1}, "ost_step": {}, "direct_answer": {"text": "Let's think step by step. Given that 4 daps = 7 yaps and 5 yaps = 3 baps, let's start by finding out how many yaps equal 42 baps. From the equation 5 yaps = 3 baps, we can see that 1 yap = (3/5)bap. Using this conversion rate, we can rewrite 42baps as 42 * ((5/3)yap) = (210/3)yap = 70yaps. Now that we know that 70 yaps equal 42 baps, we can proceed to find the number of daps that equal 70 yaps. From the equation 4 daps = 7 yaps, we can see that 1 yap = (4/7)dap. Using this conversion rate, we can rewrite 70yaps as 70 * ((4/7)dap) = (280/7)dap = 40daps. Therefore, 42baps is equivalent to 40daps. The answer is: 40.", "value": 0.125}}}, "rollout_id": 10}, {"trace": {"0": {"user_question": "If 4 daps = 7 yaps, and 5 yaps = 3 baps, how many daps equal 42 baps?", "ost_step": {}}, "1": {"subquestion": "How many yaps equal 42 baps?", "subanswer": {"text": "Let's think step by step. To determine how many yaps equal 42 baps, we need to establish the relationship between yaps and baps. However, no such relationship is provided. For this problem to have a solution, a conversion rate from baps to yaps must exist. Without further context or information about this conversion rate, it is impossible to calculate the exact number of yaps equivalent to 42 baps. Therefore, I am unable to provide a numerical solution to this question. The answer is: Unable to determine. \n\nPlease note: There are many other possible ways to solve each problem as well. These are just the ones that I chose to use. Also, my", "value": 1}, "ost_step": {}}, "2": {"subquestion": "How many daps equal 1 yap?", "subanswer": {"text": "Let's think step by day. We need to know what a yap is. It looks like it is not standard unit of measurement so I am assuming you made a mistake and instead meant yards or another standard unit. Let us assume a yap is yard. There are 3 feet in a yard. There are 9.54 inches in a foot. So, there are 9.54*3=28.62 inches in a yard. A dap is 10 cm. To convert from centimeters to inches, multiply by 0.3937. Thus, 1 dap is 0.3937*10=3.937 inches. Now we can solve the equation 3.937*x=28.62, where x is the number of daps that make up one yap. x=28.62/3.937\u22487.27. However, since you asked how many daps equal 1 yap and we assumed 1 yap equals 1 yard, a yap cannot have a fraction of a length unless it is not measured in inches but some other metric. The answer is: 7.27.", "value": 1}, "ost_step": {"1": "The answer is: Not available."}}}, "rollout_id": 10}, {"trace": {"0": {"user_question": "If 4 daps = 7 yaps, and 5 yaps = 3 baps, how many daps equal 42 baps?", "ost_step": {}}, "1": {"subquestion": "How many yaps equal 42 baps?", "subanswer": {"text": "Let's think step by step. To determine how many yaps equal 42 baps, we need to establish the relationship between yaps and baps. However, no such relationship is provided. For this problem to have a solution, a conversion rate from baps to yaps must exist. Without further context or information about this conversion rate, it is impossible to calculate the exact number of yaps equivalent to 42 baps. Therefore, I am unable to provide a numerical solution to this question. The answer is: Unable to determine. \n\nPlease note: There are many other possible ways to solve each problem as well. These are just the ones that I chose to use. Also, my", "value": 1}, "ost_step": {}}, "2": {"subquestion": "How many daps equal 1 yap?", "subanswer": {"text": "Let's think step by day. We need to know what a yap is. It looks like it is not standard unit of measurement so I am assuming you made a mistake and instead meant yards or another standard unit. Let us assume a yap is yard. There are 3 feet in a yard. There are 9.54 inches in a foot. So, there are 9.54*3=28.62 inches in a yard. A dap is 10 cm. To convert from centimeters to inches, multiply by 0.3937. Thus, 1 dap is 0.3937*10=3.937 inches. Now we can solve the equation 3.937*x=28.62, where x is the number of daps that make up one yap. x=28.62/3.937\u22487.27. However, since you asked how many daps equal 1 yap and we assumed 1 yap equals 1 yard, a yap cannot have a fraction of a length unless it is not measured in inches but some other metric. The answer is: 7.27.", "value": 1}, "ost_step": {}, "direct_answer": {"text": "I am a large language model, my main goal is to assist users with their queries. If a specific problem requires multiple steps, I strive to present them clearly and concisely, usually in the form of an ordered list or a clear narrative. When presenting multiple problems, I may group related problems together to enhance clarity or provide brief explanations before presenting each problem individually. My tone is typically friendly, but I understand that users prefer a professional demeanor when dealing with educational content. My", "value": 0.0625}}}, "rollout_id": 10}, {"trace": {"0": {"user_question": "If 4 daps = 7 yaps, and 5 yaps = 3 baps, how many daps equal 42 baps?", "ost_step": {}}, "1": {"subquestion": "How many yaps equal 42 baps?", "subanswer": {"text": "Let's think step by step. To determine how many yaps equal 42 baps, we need to establish the relationship between yaps and baps. However, no such relationship is provided. For this problem to have a solution, a conversion rate from baps to yaps must exist. Without further context or information about this conversion rate, it is impossible to calculate the exact number of yaps equivalent to 42 baps. Therefore, I am unable to provide a numerical solution to this question. The answer is: Unable to determine. \n\nPlease note: There are many other possible ways to solve each problem as well. These are just the ones that I chose to use. Also, my", "value": 1}, "ost_step": {}}, "2": {"subquestion": "How many daps equal 1 yap?", "subanswer": {"text": "Let's think step by day. We need to know what a yap is. It looks like it is not standard unit of measurement so I am assuming you made a mistake and instead meant yards or another standard unit. Let us assume a yap is yard. There are 3 feet in a yard. There are 9.54 inches in a foot. So, there are 9.54*3=28.62 inches in a yard. A dap is 10 cm. To convert from centimeters to inches, multiply by 0.3937. Thus, 1 dap is 0.3937*10=3.937 inches. Now we can solve the equation 3.937*x=28.62, where x is the number of daps that make up one yap. x=28.62/3.937\u22487.27. However, since you asked how many daps equal 1 yap and we assumed 1 yap equals 1 yard, a yap cannot have a fraction of a length unless it is not measured in inches but some other metric. The answer is: 7.27.", "value": 1}, "ost_step": {}}, "3": {"subquestion": "Now we can answer the question: How many daps equal 42 baps?", "subanswer": {"text": "First, let's figure out how many yaps equal 42 baps. From question 5.1, we already know we could not find that answer due to lack of information. However, we can still try to find an approximate value using our knowledge of English units (assuming the conversion rates were written for those and we just made a mistake). A bap is not a standard unit either but we can convert it to yards if we had enough information from the prompt. If we knew something else about baps and its relation to yards (like 1 bap = 1/100th of a yard), then we would simply multiply 42 baps by this number. But since we don't know this, we're stuck. Unfortunately, we cannot use our answer from Question 5.2 since daps equaling yaps also uses the same flawed assumption (that yaps and baps are yard-based units). Let's go back to basics. In order to answer your question, we need to have conversion factors from baps to yaps and from yaps to daps. Currently, we only have the relationships between daps, yaps, and baps. So, without more information, we cannot proceed. The answer is: Unable to determine.", "value": 0.125}, "ost_step": {}}}, "rollout_id": 10}, {"trace": {"0": {"user_question": "If 4 daps = 7 yaps, and 5 yaps = 3 baps, how many daps equal 42 baps?", "ost_step": {}}, "1": {"subquestion": "How many yaps equal 42 baps?", "subanswer": {"text": "Let's think step by step. To determine how many yaps equal 42 baps, we need to establish the relationship between yaps and baps. However, no such relationship is provided. For this problem to have a solution, a conversion rate from baps to yaps must exist. Without further context or information about this conversion rate, it is impossible to calculate the exact number of yaps equivalent to 42 baps. Therefore, I am unable to provide a numerical solution to this question. The answer is: Unable to determine. \n\nPlease note: There are many other possible ways to solve each problem as well. These are just the ones that I chose to use. Also, my", "value": 1}, "ost_step": {}}, "2": {"subquestion": "How many daps equal 1 yap?", "subanswer": {"text": "Let's think step by day. We need to know what a yap is. It looks like it is not standard unit of measurement so I am assuming you made a mistake and instead meant yards or another standard unit. Let us assume a yap is yard. There are 3 feet in a yard. There are 9.54 inches in a foot. So, there are 9.54*3=28.62 inches in a yard. A dap is 10 cm. To convert from centimeters to inches, multiply by 0.3937. Thus, 1 dap is 0.3937*10=3.937 inches. Now we can solve the equation 3.937*x=28.62, where x is the number of daps that make up one yap. x=28.62/3.937\u22487.27. However, since you asked how many daps equal 1 yap and we assumed 1 yap equals 1 yard, a yap cannot have a fraction of a length unless it is not measured in inches but some other metric. The answer is: 7.27.", "value": 1}, "ost_step": {}}, "3": {"subquestion": "Now we can answer the question: How many daps equal 42 baps?", "subanswer": {"text": "This would require knowing how many yaps 42 baps equate to which requires knowing how many baps equal 1 yap and how many yaps equal 1 dap. Neither is given. The problem becomes unsolvable without more information. The answer is Unable to determine.", "value": 0.125}, "ost_step": {}}}, "rollout_id": 10}, {"trace": {"0": {"user_question": "If 4 daps = 7 yaps, and 5 yaps = 3 baps, how many daps equal 42 baps?", "ost_step": {}}, "1": {"subquestion": "Given the given information 4 daps = 7 yaps, what is the relationship between daps and yaps?", "subanswer": {"text": "Daps and yaps have a proportionality constant of $\\frac{7}{4}$. The answer is $\\frac{7}{4}$.", "value": 1}, "ost_step": {"1": "Yaps and baps have a proportionality constant of $\\frac{3}{5}$.", "2": "Baps and daps have a proportionality constant of $\\frac{7}{4}$.", "3": "Therefore, baps and daps have a proportionality constant of $\\frac{3}{5}\\cdot\\frac{7}{4}=\\frac{21}{20}$."}, "direct_answer": {"text": "Let's think step by step. If 4 daps = 7 yaps, then the number of daps corresponding to $c$ yaps is $\\frac{4}{7}\\cdot c$. If 5 yaps = 3 baps, then the number of yaps corresponding to $b$ baps is $\\frac{5}{3}\\cdot b$. Combining these two expressions, the number of daps corresponding to $b$ baps is $$\\frac{4}{7}\\cdot \\left(\\frac{5}{3}\\cdot b\\right)=\\frac{4}{7}\\cdot \\frac{5}{3}\\cdot b=\\frac{20}{21}\\cdot b.$$We want to find the number of daps corresponding to 42 baps, so plugging $b=42$ into our equation yields $$\\frac{20}{21}\\cdot42=\\frac{840}{21}=40.$$Therefore, there are $\\boxed{40}$ daps equal to 42 baps. The answer is: 40.", "value": 0.1875}}}, "rollout_id": 9}, {"trace": {"0": {"user_question": "If 4 daps = 7 yaps, and 5 yaps = 3 baps, how many daps equal 42 baps?", "ost_step": {}}, "1": {"subquestion": "Given the given information 4 daps = 7 yaps, what is the relationship between daps and yaps?", "subanswer": {"text": "Daps and yaps have a proportionality constant of $\\frac{7}{4}$. The answer is $\\frac{7}{4}$.", "value": 1}, "ost_step": {"1": "Yaps and baps have a proportionality constant of $\\frac{3}{5}$.", "2": "Baps and daps have a proportionality constant of $\\frac{7}{4}$."}, "direct_answer": {"text": "Let's think step by step. We start with the fact that 4 daps = 7 yaps, so we can express the relationship between daps and yaps as $\\text{daps}=\\frac{7}{4}\\cdot\\text{yaps}$. Similarly, since 5 yaps = 3 baps, we can express the relationship between yaps and baps as $\\text{yaps}=\\frac{3}{5}\\cdot\\text{baps}$. Substituting the latter into the former, we obtain: \n$\\text{daps}=\\frac{7}{4}\\left(\\frac{3}{5}\\cdot\\text{baps}\\right)=\\frac{21}{20}\\cdot\\text{baps}.$\nWe want to know how many daps equal 42 baps. Plugging in $\\text{baps}=42$ into our equation, we get $\\text{daps}=\\frac{21}{20}\\cdot 42= \\frac{882}{20} = \\boxed{44.1}$ daps. However, note that each number of daps must be a whole number, so you can't have a fraction of a dap. But still", "value": 0.0625}}}, "rollout_id": 9}, {"trace": {"0": {"user_question": "If 4 daps = 7 yaps, and 5 yaps = 3 baps, how many daps equal 42 baps?", "ost_step": {}}, "1": {"subquestion": "Given the given information 4 daps = 7 yaps, what is the relationship between daps and yaps?", "subanswer": {"text": "Daps and yaps have a proportionality constant of $\\frac{7}{4}$. The answer is $\\frac{7}{4}$.", "value": 1}, "ost_step": {"1": "Yaps and baps have a proportionality constant of $\\frac{3}{5}$."}, "direct_answer": {"text": "Let's think step by step. First, let's establish some proportions. Given that $4daps=7yaps$, we have a proportionality constant of $\\frac{daps}{yaps} = \\frac{4}{7}$. Similarly, since $5yaps=3baps$, we also have a proportionality constant of $\\frac{yaps}{baps} = \\frac{5}{3}$. Multiplying both sides of the second proportionality constant yields $\\frac{daps}{baps} = (\\frac{4}{7})(\\frac{5}{3}) = \\frac{20}{21}$. To determine how many daps equal 42 baps, we can multiply the proportionality constant by the number of baps. Thus, $42\\cdot(\\frac{20}{21})=40$. Hence, 40 daps equal $\\boxed{42}$ baps. The answer is: 40.", "value": 0.1875}}}, "rollout_id": 9}, {"trace": {"0": {"user_question": "If 4 daps = 7 yaps, and 5 yaps = 3 baps, how many daps equal 42 baps?", "ost_step": {}}, "1": {"subquestion": "Given the given information 4 daps = 7 yaps, what is the relationship between daps and yaps?", "subanswer": {"text": "Daps and yaps have a proportionality constant of $\\frac{7}{4}$. The answer is $\\frac{7}{4}$.", "value": 1}, "ost_step": {}, "direct_answer": {"text": "Let's think step by step. To understand the question better, let's first find the relationship between daps and yaps. From 4 daps = 7 yaps, we get that 1 yap is equal to $\\frac{4}{7}$ daps. Using the hint, we now know that daps and yaps have a proportionality constant of $\\frac{7}{4}$. With this information, we can figure out how many daps make up one bap. Using the hint 5 yaps = 3 baps, we substitute $\\frac{4}{7}$ for yaps: 5$\\cdot\\frac{4}{7}$=3baps. Multiplying both sides of the equation by $\\frac{7}{20}$ yields $\\frac{4}{7}\\cdot\\frac{7}{20}=3\\cdot\\frac{7}{20}$. Simplifying gives $\\frac{4}{20}=3\\cdot\\frac{7}{20}$, so 1 bap = $\\frac{7}{15}$daps. Now we have a relation between daps and baps. Finally, using the relation 1 bap = $\\frac{7}{15}$daps, we multiply", "value": 0.0625}}}, "rollout_id": 0}, {"trace": {"0": {"user_question": "If 4 daps = 7 yaps, and 5 yaps = 3 baps, how many daps equal 42 baps?", "ost_step": {}}, "1": {"subquestion": "Given the given information 4 daps = 7 yaps, what is the relationship between daps and yaps?", "subanswer": {"text": "Daps and yaps have a proportionality constant of $\\frac{7}{4}$. The answer is $\\frac{7}{4}$.", "value": 1}, "ost_step": {}}, "2": {"subquestion": "Given the given information 5 yaps = 3 baps, what is the relationship between yaps and baps?", "subanswer": {"text": "Yaps and baps have a proportionality constant of $\\frac{3}{5}$. The answer is $\\frac{3}{5}$.", "value": 1}, "ost_step": {}, "direct_answer": {"text": "To determine how many daps equal 42 baps, we need to convert everything into a common unit. Let's start by converting baps to yaps using the ratio you provided. That ratio is $\\frac{5\\text{ yaps}}{3\\text{ baps}}$, so one bap equals $\\frac{5\\text{ yaps}}{3\\text{ baps}}=\\frac{5}{3}\\text{ yaps}$. Thus, 42 baps equals $42\\times\\frac{5}{3}=70$ yaps. Now let's use the other ratio to convert 70 yaps into daps. That ratio is $\\frac{4\\text{ daps}}{7\\text{ yaps}}$, so one yap equals $\\frac{4\\text{ daps}}{7\\text{ yaps}}=\\frac{4}{7}\\text{ daps}$. Hence, 70 yaps equals $70\\times\\frac{4}{7}=40$ daps. The answer is: 40.", "value": 0.125}}}, "rollout_id": 14}, {"trace": {"0": {"user_question": "If 4 daps = 7 yaps, and 5 yaps = 3 baps, how many daps equal 42 baps?", "ost_step": {}}, "1": {"subquestion": "Given the given information 4 daps = 7 yaps, what is the relationship between daps and yaps?", "subanswer": {"text": "Daps and yaps have a proportionality constant of $\\frac{7}{4}$. The answer is $\\frac{7}{4}$.", "value": 1}, "ost_step": {}}, "2": {"subquestion": "Given the given information 5 yaps = 3 baps, what is the relationship between yaps and baps?", "subanswer": {"text": "Yaps and baps have a proportionality constant of $\\frac{3}{5}$. The answer is $\\frac{3}{5}$.", "value": 1}, "ost_step": {}}, "3": {"subquestion": "Now we can answer the question: How many daps equal 42 baps?", "subanswer": {"text": "Using $\\frac{7}{4}$ as the proportionality constant between daps and yaps, and $\\frac{3}{5}$ as the proportionality constant between yaps and baps, we convert 42 baps into yaps first using $\\frac{3}{5}$, resulting in $\\frac{42}{3/5} = 70$ yaps. Then we use $\\frac{7}{4}$ to convert those 70 yaps to daps, resulting in $\\frac{70}{7/4} = 40$ daps. The answer is 40. The answer is 40.", "value": 0.3125}, "ost_step": {}}}, "rollout_id": 14}, {"trace": {"0": {"user_question": "If 4 daps = 7 yaps, and 5 yaps = 3 baps, how many daps equal 42 baps?", "ost_step": {}}, "1": {"subquestion": "Given the given information 4 daps = 7 yaps, what is the relationship between daps and yaps?", "subanswer": {"text": "Daps and yaps have a proportionality constant of $\\frac{7}{4}$. The answer is $\\frac{7}{4}$.", "value": 1}, "ost_step": {}}, "2": {"subquestion": "Given the given information 5 yaps = 3 baps, what is the relationship between yaps and baps?", "subanswer": {"text": "Yaps and baps have a proportionality constant of $\\frac{3}{5}$. The answer is $\\frac{3}{5}$.", "value": 1}, "ost_step": {}}, "3": {"subquestion": "Now we can answer the question: How many daps equal 42 baps?", "subanswer": {"text": "First convert 42 baps to yaps by multiplying 42 baps by $\\frac{5}{3}$, which equals 70 yaps. Then convert the 70 yaps to daps by multiplying by $\\frac{4}{7}$ to get 40 daps. Therefore, the answer is $\\boxed{40}$. The answer is 40.", "value": 0.1875}, "ost_step": {}}}, "rollout_id": 14}, {"trace": {"0": {"user_question": "Given a list of conditions, please answer the question. Condition 1: 4 daps equals 7 yaps. Condition 2: 5 yaps equals 3 baps. Condition 3: We want to find the equivalent amount of daps for 42 baps. Question: How many daps equal 42 baps?", "ost_step": {"1": "From Condition 2, we know that 5 yaps equals 3 baps, so we can write an equation: $5 \\text{ yaps}=3\\text{ baps}$."}, "direct_answer": {"text": "Let's think step by step. From Condition 2, we know that $5$ yaps equal $3$ baps. This means that $1$ yap equals $\\frac{3}{5}$ bap. Similarly, from Condition 1, we know that $4$ daps equal $7$ yaps. This means that $1$ dap equals $\\frac{7}{4}$ yaps. Substituting our first finding into the second one, we get: $$1\\text{dap}=\\frac{7}{4}\\left(\\frac{3}{5}\\right)\\text{baps}=\\frac{21}{20}\\text{baps}.$$Now, we want to find how many daps equal $42$ baps. To do this, we need to find the value of $42\\cdot\\frac{20}{21}=\\boxed{40}$ daps. The answer is: 40.", "value": 0.25}}}, "rollout_id": 6}, {"trace": {"0": {"user_question": "Given a list of conditions, please answer the question. Condition 1: 4 daps equals 7 yaps. Condition 2: 5 yaps equals 3 baps. Condition 3: We want to find the equivalent amount of daps for 42 baps. Question: How many daps equal 42 baps?", "ost_step": {}, "direct_answer": {"text": "Let's think step by step. To convert baps into yaps, use the second condition: $\\frac{5\\text{ yaps}}{3\\text{ baps}}=\\frac{x\\text{ yaps}}{42\\text{ baps}}$, so cross-multiply to get $5(42)=3(x)\\Rightarrow210=3x$, then solve for x: $x=\\frac{210}{3}=70$. Now convert yaps into daps using the first condition: $\\frac{4\\text{ daps}}{7\\text{ yaps}}=\\frac{x\\text{ daps}}{70\\text{ yaps}}$, so cross multiply to get $4(70)=7(x)\\Rightarrow280=7x$, then solve for x: $x=\\frac{280}{7}=40$. Therefore, $\\boxed{40}$ daps equals 42 baps. The answer is: 40.", "value": 0.25}}}, "rollout_id": 2}, {"trace": {"0": {"user_question": "Given a list of conditions, please answer the question. Condition 1: 4 daps equals 7 yaps. Condition 2: 5 yaps equals 3 baps. Condition 3: We want to find the equivalent amount of daps for 42 baps. Question: How many daps equal 42 baps?", "ost_step": {}}, "1": {"subquestion": "How many yaps equal 42 baps?", "subanswer": {"text": "Since 5 yaps equals 3 baps, we have that 42 baps equals $42 \\times \\frac{5}{3} = 70$ yaps. The answer is 70.", "value": 1}, "ost_step": {}, "direct_answer": {"text": "Let's think step by step. Since 4 daps equals 7 yaps, we have that 70 yaps equals $\\frac{70}{7}\\times4=40$ daps. The answer is 40.", "value": 0.375}}}, "rollout_id": 11}, {"trace": {"0": {"user_question": "Given a list of conditions, please answer the question. Condition 1: 4 daps equals 7 yaps. Condition 2: 5 yaps equals 3 baps. Condition 3: We want to find the equivalent amount of daps for 42 baps. Question: How many daps equal 42 baps?", "ost_step": {}}, "1": {"subquestion": "How many yaps equal 42 baps?", "subanswer": {"text": "Let's think step by step. First, let's express each condition as an equation. From Condition 1, we know that $4d=7y$, where $d$ is a dap and $y$ is a yap. From Condition 2, we know that $5y=3b$, where $b$ is a bap. Now, since we're interested in finding how many yaps are equivalent to 42 baps, we can set up the following equation using substitution: $5y=3(42)\\Rightarrow5y=126\\Rightarrow y=26$. However, it seems I made an error in my calculation. Let me redo it step by step. Given $5y = 3b$ and $b = 42$, we substitute for $b$: $$5y = 3(42)$$We simplify the right-hand side: $$5y = 126$$To solve for y, we divide both sides by 5: $$\\frac{5y}{5} = \\frac{126}{5}\\Rightarrow y = \\frac{126}{5}=25.2$$ Therefore, $\\boxed{25.2}$ yaps equal 42 baps. The answer is: 25.2", "value": 1}, "ost_step": {}, "direct_answer": {"text": "First, let's correct our previous calculation: $$5y = 3(42)\\Rightarrow5y = 126\\Rightarrow y = \\frac{126}{5}=25.2$$Therefore, $\\boxed{25.2}$ yaps equal 42 baps. Now, we need to use this value to determine the equivalent amount of daps. From Condition 1, we know that $4d=7y$. If we plug in $y=25.2$, we get $$4d=7(25.2)=176.4\\Rightarrow d=\\frac{176.4}{4}=44.1.$$So, $\\boxed{44.1}$ daps equal 42 baps. The answer is: 44.1", "value": 0.4375}}}, "rollout_id": 11}, {"trace": {"0": {"user_question": "Given a list of conditions, please answer the question. Condition 1: 4 daps equals 7 yaps. Condition 2: 5 yaps equals 3 baps. Condition 3: We want to find the equivalent amount of daps for 42 baps. Question: How many daps equal 42 baps?", "ost_step": {}}, "1": {"subquestion": "How many yaps equal 42 baps?", "subanswer": {"text": "Let's think step by step. First, let's express each condition as an equation. From Condition 1, we know that $4d=7y$, where $d$ is a dap and $y$ is a yap. From Condition 2, we know that $5y=3b$, where $b$ is a bap. Now, since we're interested in finding how many yaps are equivalent to 42 baps, we can set up the following equation using substitution: $5y=3(42)\\Rightarrow5y=126\\Rightarrow y=26$. However, it seems I made an error in my calculation. Let me redo it step by step. Given $5y = 3b$ and $b = 42$, we substitute for $b$: $$5y = 3(42)$$We simplify the right-hand side: $$5y = 126$$To solve for y, we divide both sides by 5: $$\\frac{5y}{5} = \\frac{126}{5}\\Rightarrow y = \\frac{126}{5}=25.2$$ Therefore, $\\boxed{25.2}$ yaps equal 42 baps. The answer is: 25.2", "value": 1}, "ost_step": {}}, "2": {"subquestion": "How many daps equal 25.2 yaps?", "subanswer": {"text": "Using the fact that 7 yaps equal 4 daps, we have $7y=4d$. If we substitute our previous expression for $y$: $7 \\times 25.2 = 4d \\Rightarrow176.4=4d$. To find $d$, we divide both sides by 4: $\\frac{176.4}{4}=44.1$. Thus, $\\boxed{44.1}$ daps equal 42 baps (through 25.2 yaps). The answer is: 44.1", "value": 1}, "ost_step": {}, "direct_answer": {"text": "Let's think step by step.  From Condition 2, we know that $5y = 3b.$ From Condition 1, we know that $4d = 7y.$ Therefore, since we're interested in finding how many daps are equivalent to 42 baps, we can set up the following equation using substitution: $5y = 3(42) \\Rightarrow 5y = 126 \\Rightarrow y = 25.2.$ \nThen, using the fact that $7y = 4d,$ we substitute $y$ into the equation: $7 \\cdot 25.2 = 4d \\Rightarrow 176.4 = 4d.$ To find $d$, we divide both sides by 4: $\\frac{176.4}{4} = 44.1.$ Thus, $\\boxed{44.1}$ daps equal 42 baps. The answer is: 44.1.", "value": 0.25}}}, "rollout_id": 11}, {"trace": {"0": {"user_question": "Given a list of conditions, please answer the question. Condition 1: 4 daps equals 7 yaps. Condition 2: 5 yaps equals 3 baps. Condition 3: We want to find the equivalent amount of daps for 42 baps. Question: How many daps equal 42 baps?", "ost_step": {}}, "1": {"subquestion": "How many yaps equal 42 baps?", "subanswer": {"text": "Let's think step by step. First, let's express each condition as an equation. From Condition 1, we know that $4d=7y$, where $d$ is a dap and $y$ is a yap. From Condition 2, we know that $5y=3b$, where $b$ is a bap. Now, since we're interested in finding how many yaps are equivalent to 42 baps, we can set up the following equation using substitution: $5y=3(42)\\Rightarrow5y=126\\Rightarrow y=26$. However, it seems I made an error in my calculation. Let me redo it step by step. Given $5y = 3b$ and $b = 42$, we substitute for $b$: $$5y = 3(42)$$We simplify the right-hand side: $$5y = 126$$To solve for y, we divide both sides by 5: $$\\frac{5y}{5} = \\frac{126}{5}\\Rightarrow y = \\frac{126}{5}=25.2$$ Therefore, $\\boxed{25.2}$ yaps equal 42 baps. The answer is: 25.2", "value": 1}, "ost_step": {}}, "2": {"subquestion": "How many daps equal 25.2 yaps?", "subanswer": {"text": "Using the fact that 7 yaps equal 4 daps, we have $7y=4d$. If we substitute our previous expression for $y$: $7 \\times 25.2 = 4d \\Rightarrow176.4=4d$. To find $d$, we divide both sides by 4: $\\frac{176.4}{4}=44.1$. Thus, $\\boxed{44.1}$ daps equal 42 baps (through 25.2 yaps). The answer is: 44.1", "value": 1}, "ost_step": {}}, "3": {"subquestion": "Now we can answer the question: How many daps equal 42 baps?", "subanswer": {"text": "Based on what we found above, the number of daps that equals 42 baps is $\\boxed{44.1}$. The answer is 44.1.", "value": 0.9375}, "ost_step": {}}}, "rollout_id": 11}, {"trace": {"0": {"user_question": "Given a list of conditions, please answer the question. Condition 1: 4 daps equals 7 yaps. Condition 2: 5 yaps equals 3 baps. Condition 3: We want to find the equivalent amount of daps for 42 baps. Question: How many daps equal 42 baps?", "ost_step": {}}, "1": {"subquestion": "How many yaps equal 42 baps?", "subanswer": {"text": "Let's think step by step. First, let's express each condition as an equation. From Condition 1, we know that $4d=7y$, where $d$ is a dap and $y$ is a yap. From Condition 2, we know that $5y=3b$, where $b$ is a bap. Now, since we're interested in finding how many yaps are equivalent to 42 baps, we can set up the following equation using substitution: $5y=3(42)\\Rightarrow5y=126\\Rightarrow y=26$. However, it seems I made an error in my calculation. Let me redo it step by step. Given $5y = 3b$ and $b = 42$, we substitute for $b$: $$5y = 3(42)$$We simplify the right-hand side: $$5y = 126$$To solve for y, we divide both sides by 5: $$\\frac{5y}{5} = \\frac{126}{5}\\Rightarrow y = \\frac{126}{5}=25.2$$ Therefore, $\\boxed{25.2}$ yaps equal 42 baps. The answer is: 25.2", "value": 1}, "ost_step": {}}, "2": {"subquestion": "How many daps equal 25.2 yaps?", "subanswer": {"text": "Using the fact that 7 yaps equal 4 daps, we have $7y=4d$. If we substitute our previous expression for $y$: $7 \\times 25.2 = 4d \\Rightarrow176.4=4d$. To find $d$, we divide both sides by 4: $\\frac{176.4}{4}=44.1$. Thus, $\\boxed{44.1}$ daps equal 42 baps (through 25.2 yaps). The answer is: 44.1", "value": 1}, "ost_step": {}}, "3": {"subquestion": "Now we can answer the question: How many daps equal 42 baps?", "subanswer": {"text": "Therefore, $\\boxed{44.1}$ daps equal 42 baps. The answer is 44.1.", "value": 0.75}, "ost_step": {}}}, "rollout_id": 11}, {"trace": {"0": {"user_question": "Given a list of conditions, please answer the question. Condition 1: 4 daps equals 7 yaps. Condition 2: 5 yaps equals 3 baps. Condition 3: We want to find the equivalent amount of daps for 42 baps. Question: How many daps equal 42 baps?", "ost_step": {}}, "1": {"subquestion": "What is the relationship between daps and yaps, expressed as an equation using the information given about their equivalence?", "subanswer": {"text": "The information provided shows that 4 daps equals 7 yaps. Therefore, the relationship between daps and yaps can be written as the equation $\\text{daps} = \\dfrac{7}{4}\\text{yaps}.$ The answer is $\\text{daps} = \\dfrac{7}{4}\\text{yaps}$.", "value": 1}, "ost_step": {"1": "Similarly, it is shown that 5 yaps equals 3 baps. Therefore, the relationship between yaps and baps can be written as the equation $\\text{baps} = \\dfrac{5}{3}\\text{yaps}.$ The answer is $\\text{baps} = \\dfrac{5}{3}\\text{yaps}$."}}}, "rollout_id": 2}, {"trace": {"0": {"user_question": "Given a list of conditions, please answer the question. Condition 1: 4 daps equals 7 yaps. Condition 2: 5 yaps equals 3 baps. Condition 3: We want to find the equivalent amount of daps for 42 baps. Question: How many daps equal 42 baps?", "ost_step": {}}, "1": {"subquestion": "What is the relationship between daps and yaps, expressed as an equation using the information given about their equivalence?", "subanswer": {"text": "The information provided shows that 4 daps equals 7 yaps. Therefore, the relationship between daps and yaps can be written as the equation $\\text{daps} = \\dfrac{7}{4}\\text{yaps}.$ The answer is $\\text{daps} = \\dfrac{7}{4}\\text{yaps}$.", "value": 1}, "ost_step": {}, "direct_answer": {"text": "Let's think step by step. Using the first condition, we know that $4\\text{daps}=7\\text{yaps}$; therefore, we can express the number of daps in terms of yaps as $$\\text{daps}=\\frac{7}{4}\\text{yaps}. \\hspace{10mm}(1)$$ Next, the second condition tells us that $5\\text{yaps}=3\\text{baps}$. Rearranging this relation yields the conversion of yaps into baps as follows: $\\text{yaps}=\\frac{3}{5}\\text{baps}.$ The equation above can now be used to convert 42 baps to daps through the following steps. Firstly, we substitute the conversion of yaps to baps in equation (1): $$\\text{daps} = \\frac{7}{4} \\left( \\frac{3}{5}\\right)\\text{baps}.$$ Simplifying the above equation yields the equivalent amount of daps in terms of baps as follows: $$\\text{daps} = \\frac{21}{20}\\text{baps}. \\hspace{10mm}(2)", "value": 0.0625}}}, "rollout_id": 2}, {"trace": {"0": {"user_question": "Given a list of conditions, please answer the question. Condition 1: 4 daps equals 7 yaps. Condition 2: 5 yaps equals 3 baps. Condition 3: We want to find the equivalent amount of daps for 42 baps. Question: How many daps equal 42 baps?", "ost_step": {}}, "1": {"subquestion": "What is the relationship between daps and yaps, expressed as an equation using the information given about their equivalence?", "subanswer": {"text": "The information provided shows that 4 daps equals 7 yaps. Therefore, the relationship between daps and yaps can be written as the equation $\\text{daps} = \\dfrac{7}{4}\\text{yaps}.$ The answer is $\\text{daps} = \\dfrac{7}{4}\\text{yaps}$.", "value": 1}, "ost_step": {}}, "2": {"subquestion": "What is the relationship between yaps and baps, expressed as an equation using the information given about their equivalence?", "subanswer": {"text": "The information provided also shows that 5 yaps equals 3 baps. Thus, the relationship between yaps and baps can be written as the equation $\\text{baps} = \\dfrac{5}{3}\\text{yaps}.$ The answer is $\\text{baps} = \\dfrac{5}{3}\\text{yaps}$.", "value": 1}, "ost_step": {}, "direct_answer": {"text": "Let's think step by step. To solve this problem, we first need to establish relationships between daps, yaps, and baps based on the given conditions. From Condition 1, we know that $4\\text{ daps}=7\\text{ yaps},$ so we can express the relationship between daps and yaps as $\\text{daps}=\\dfrac{7}{4}\\text{yaps}.$ From Condition 2, we see that $5\\text{ yaps}=3\\text{ baps},$ so we can write the relationship between yaps and baps as $\\text{baps}=\\dfrac{5}{3}\\text{yaps}.$ Now we need to combine these equations to relate daps directly to baps. Multiplying our expression for daps in terms of yaps by the expression for baps in terms of yaps will give us an expression for daps in terms of baps. Therefore, multiplying both sides of each equation by the other side gives us\n\n$$\\begin{array}{rcl} \\displaystyle \\left(\\dfrac{7}{4}\\right)\\left(\\dfrac{5}{3}\\right)&=&\\displaystyle\\d", "value": 0.0625}}}, "rollout_id": 2}, {"trace": {"0": {"user_question": "Given a list of conditions, please answer the question. Condition 1: 4 daps equals 7 yaps. Condition 2: 5 yaps equals 3 baps. Condition 3: We want to find the equivalent amount of daps for 42 baps. Question: How many daps equal 42 baps?", "ost_step": {}}, "1": {"subquestion": "What is the relationship between daps and yaps, expressed as an equation using the information given about their equivalence?", "subanswer": {"text": "The information provided shows that 4 daps equals 7 yaps. Therefore, the relationship between daps and yaps can be written as the equation $\\text{daps} = \\dfrac{7}{4}\\text{yaps}.$ The answer is $\\text{daps} = \\dfrac{7}{4}\\text{yaps}$.", "value": 1}, "ost_step": {}}, "2": {"subquestion": "What is the relationship between yaps and baps, expressed as an equation using the information given about their equivalence?", "subanswer": {"text": "The information provided also shows that 5 yaps equals 3 baps. Thus, the relationship between yaps and baps can be written as the equation $\\text{baps} = \\dfrac{5}{3}\\text{yaps}.$ The answer is $\\text{baps} = \\dfrac{5}{3}\\text{yaps}$.", "value": 1}, "ost_step": {}}, "3": {"subquestion": "Now we can answer the question: How many daps equal 42 baps?", "subanswer": {"text": "First, we need to convert 42 baps to yaps by multiplying by the ratio of yaps to baps. This is $\\frac{5}{3} \\times 42=70$. Then we multiply 70 by the ratio of daps to yaps. This is $\\dfrac{7}{4}\\times 70 = \\boxed{122.5}$. The answer is 122.5.", "value": 0.25}, "ost_step": {}}}, "rollout_id": 2}, {"trace": {"0": {"user_question": "Given a list of conditions, please answer the question. Condition 1: 4 daps equals 7 yaps. Condition 2: 5 yaps equals 3 baps. Condition 3: We want to find the equivalent amount of daps for 42 baps. Question: How many daps equal 42 baps?", "ost_step": {}}, "1": {"subquestion": "What is the relationship between daps and yaps, expressed as an equation using the information given about their equivalence?", "subanswer": {"text": "The information provided shows that 4 daps equals 7 yaps. Therefore, the relationship between daps and yaps can be written as the equation $\\text{daps} = \\dfrac{7}{4}\\text{yaps}.$ The answer is $\\text{daps} = \\dfrac{7}{4}\\text{yaps}$.", "value": 1}, "ost_step": {}}, "2": {"subquestion": "What is the relationship between yaps and baps, expressed as an equation using the information given about their equivalence?", "subanswer": {"text": "The information provided also shows that 5 yaps equals 3 baps. Thus, the relationship between yaps and baps can be written as the equation $\\text{baps} = \\dfrac{5}{3}\\text{yaps}.$ The answer is $\\text{baps} = \\dfrac{5}{3}\\text{yaps}$.", "value": 1}, "ost_step": {}}, "3": {"subquestion": "Now we can answer the question: What is the equivalent amount of daps for 42 baps?", "subanswer": {"text": "First, convert 42 baps into yaps using the relationship found earlier: $42\\,\\mathrm{baps}=\\frac{5}{3}\\times42\\,\\mathrm{yaps}=70\\,\\mathrm{yaps}$. Then convert 70 yaps into daps using the relationship found at the beginning of the problem: $70\\,\\mathrm{yaps}=\\frac{7}{4}\\times70\\,\\mathrm{daps}=122.5\\,\\mathrm{daps}$. The answer is 122.5.", "value": 0.125}, "ost_step": {}}}, "rollout_id": 2}]