[{"trace": {"0": {"user_question": "What is the smallest real number $x$ in the domain of the function $$g(x) = \\sqrt{(x-3)^2-(x-8)^2}~?$$", "ost_step": {"1": "For the expression inside the square root to be nonnegative, $(x-3)^2 - (x-8)^2\\geq0$.", "2": "Simplifying, we get $(x^2-6x+9)-(x^2-16x+64)\\geq0$, or $10x-55\\geq0$.", "3": "Dividing both sides by 10, we obtain $x-\\frac{55}{10}\\geq 0$, so $x\\geq \\frac{11}{2}$.", "4": "Therefore, the domain of the function $g(x)$ is all real numbers $x$ such that $x\\geq \\frac{11}{2}$."}, "direct_answer": {"text": "Let's think step by step. To determine the domain of the function $g(x)=\\sqrt{(x-3)^2-(x-8)^2},$ we need to ensure that the expression inside the radical is nonnegative. For this purpose, let's start by simplifying the expression. We see that $(x-3)^2-(x-8)^2=(x-3+x-8)(x-3-x+8)=(2x-11)(5).$ Thus, to keep the expression inside the radical nonnegative, it suffices to require that $2x-11\\geq 0,$ since $(5)>0.$ Solving the inequality $2x-11\\geq 0,$ we get $x\\geq\\frac{11}{2}.$ Hence, the domain of the function $g(x)$ is $\\left[\\frac{11}{2},\\infty\\right)$ and the smallest real number in the domain is $\\boxed{\\frac{11}{2}}$. The answer is: \\frac{11}{2}.", "value": 0.4375}}}, "rollout_id": 10}, {"trace": {"0": {"user_question": "What is the smallest real number $x$ in the domain of the function $$g(x) = \\sqrt{(x-3)^2-(x-8)^2}~?$$", "ost_step": {"1": "For the expression inside the square root to be nonnegative, $(x-3)^2 - (x-8)^2\\geq0$.", "2": "Simplifying, we get $(x^2-6x+9)-(x^2-16x+64)\\geq0$, or $10x-55\\geq0$.", "3": "Dividing both sides by 10, we obtain $x-\\frac{55}{10}\\geq 0$, so $x\\geq \\frac{11}{2}$."}, "direct_answer": {"text": "Let's think step by step. We need $(x-3)^2-(x-8)^2\\geq0$ for the function $g(x)$ to be defined because the expression inside a square root cannot be negative. By expanding both squares, we get $(x-3)(x-3)-(x-8)(x-8)\\geq0$. This simplifies to $x^2-6x+9-x^2+16x-64\\geq0$, or $10x-55\\geq0$. When we solve the inequality, we get that $x\\geq \\frac{11}{2}.$ Since we're looking for the smallest value of $x$, we take the smallest possible value that satisfies the inequality. Thus, the answer is $x=\\frac{11}{2}$. The answer is: $\\frac{11}{2}$.", "value": 0.4375}}}, "rollout_id": 10}, {"trace": {"0": {"user_question": "What is the smallest real number $x$ in the domain of the function $$g(x) = \\sqrt{(x-3)^2-(x-8)^2}~?$$", "ost_step": {"1": "For the expression inside the square root to be nonnegative, $(x-3)^2 - (x-8)^2\\geq0$.", "2": "Simplifying, we get $(x^2-6x+9)-(x^2-16x+64)\\geq0$, or $10x-55\\geq0$."}, "direct_answer": {"text": "Let's think step by step. The expression inside the square root must be nonnegative, so we need to solve the inequality $(x-3)^2 - (x-8)^2 \\geq 0$. Expanding the squares, we get $x^2 - 6x + 9 - x^2 + 16x - 64 \\geq 0$. Combining like terms yields $10x - 55 \\geq 0$. Solving for $x$, we add 55 to both sides and obtain $10x \\geq 55$. Finally, dividing by 10 gives us $x \\geq \\frac{55}{10} = \\frac{11}{2}.$ Therefore, the smallest real number $x$ in the domain of the function is $\\frac{11}{2}$. The answer is: 11/2.", "value": 0.8125}}}, "rollout_id": 7}, {"trace": {"0": {"user_question": "What is the smallest real number $x$ in the domain of the function $$g(x) = \\sqrt{(x-3)^2-(x-8)^2}~?$$", "ost_step": {"1": "For the expression inside the square root to be nonnegative, $(x-3)^2 - (x-8)^2\\geq0$."}, "direct_answer": {"text": "Let's think step by step. We want the expression inside the square root to be non-negative. That is, $(x-3)^2-(x-8)^2\\geq0$. This simplifies to $(x^2-6x+9)-(x^2-16x+64)\\geq0$. Cancelling like terms yields $10x-55\\geq0$. Subtracting 55 from both sides gives us $10x\\geq55$. Dividing both sides by 10 gives us $x\\geq\\frac{55}{10}=5.5$. Now that we know the minimum value of x, let's consider the original problem again. The question asks for the **smallest** real number in the domain, so $x=5.5$ is our solution. The answer is: 5.5.", "value": 0.3125}}}, "rollout_id": 0}, {"trace": {"0": {"user_question": "What is the smallest real number $x$ in the domain of the function $$g(x) = \\sqrt{(x-3)^2-(x-8)^2}~?$$", "ost_step": {}, "direct_answer": {"text": "Let's think step by step. To determine the domain of $g,$ we first note that both $(x-3)^2$ and $(x-8)^2$ are always nonnegative since they're perfect squares. Subtracting one from the other is also nonnegative since we're dealing with perfect square differences which can't be negative. So $$(x-3)^2-(x-8)^2\\geq0.$$We need to solve this inequality. Using difference of squares, we get: $$(x^2-6x+9)-(x^2-16x+64)=10x-55\\geq0,$$which implies that $$10x-55\\geq0\\implies x\\geq5.5.$$Therefore, the smallest value that satisfies this condition is $\\boxed{x=5.5}$ since it is the lowest possible value of $x$ for this function to be defined. The answer is: 5.5.", "value": 0.125}}}, "rollout_id": 0}, {"trace": {"0": {"user_question": "What is the smallest real number $x$ in the domain of the function $$g(x) = \\sqrt{(x-3)^2-(x-8)^2}~?$$", "ost_step": {}}, "1": {"subquestion": "What expression is inside the square root in the function $g(x)$?", "subanswer": {"text": "It's $(x-3)^2-(x-8)^2$. The answer is $(x-3)^2-(x-8)^2$.", "value": 1}, "ost_step": {}, "direct_answer": {"text": "Let's think step by step. To determine the domain of the function $g$, we need to ensure that the value inside the square root is nonnegative. That is, we want $(x-3)^2-(x-8)^2\\geq0$. Expanding the squares on both sides, we get $$(x^2-6x+9)-(x^2-16x+64)\\geq0.$$Simplifying further yields $$10x-55\\geq0,$$or equivalently,$$\\boxed{x\\geq\\frac{55}{10}=11/2}.$$So, the smallest real number $x$ in the domain of the function $g(x)=\\sqrt{(x-3)^2-(x-8)^2}$ is $\\frac{55}{10}=11/2$. The answer is: 11/2.", "value": 0.25}}}, "rollout_id": 1}, {"trace": {"0": {"user_question": "What is the smallest real number $x$ in the domain of the function $$g(x) = \\sqrt{(x-3)^2-(x-8)^2}~?$$", "ost_step": {}}, "1": {"subquestion": "What expression is inside the square root in the function $g(x)$?", "subanswer": {"text": "It's $(x-3)^2-(x-8)^2$. The answer is $(x-3)^2-(x-8)^2$.", "value": 1}, "ost_step": {}}, "2": {"subquestion": "What is the difference of squares formula?", "subanswer": {"text": "The difference of squares is $a^2 - b^2=(ab)(a+b)$. The answer is $(ab)(a+b)$.", "value": 1}, "ost_step": {}, "direct_answer": {"text": "Let's think step by step. By applying the difference of squares formula, we see that the expression inside the square root can be written as\n\\begin{align*}\n(x-3)^2-(x-8)^2&=\\left((x-3)+(x-8)\\right)\\left((x-3)-(x-8)\\right)\\\\\n&=(x-3+x-8)(x-3-x+8)\\\\\n&=(2x-11)(5).\n\\end{align*}Therefore, the original equation becomes\n\\[g(x)=\\sqrt{(2x-11)(5)}.\\]\nTo make sure that $g(x)$ is defined, it must be true that $(2x-11)(5)\\geq0$, so $2x-11\\geq0$, giving $x\\geq\\frac{11}{2}$. Moreover, since $x$ cannot equal $\\frac{11}{2}$ itself (it would require $2x-11=0$ to do so), we see that $x>\\frac{11}{2}$.\nTherefore, the answer is $\\frac{11}{2}$. The answer is: \\frac{11}{2}.", "value": 0.125}}}, "rollout_id": 11}, {"trace": {"0": {"user_question": "What is the smallest real number $x$ in the domain of the function $$g(x) = \\sqrt{(x-3)^2-(x-8)^2}~?$$", "ost_step": {}}, "1": {"subquestion": "What expression is inside the square root in the function $g(x)$?", "subanswer": {"text": "It's $(x-3)^2-(x-8)^2$. The answer is $(x-3)^2-(x-8)^2$.", "value": 1}, "ost_step": {}}, "2": {"subquestion": "What is the difference of squares formula?", "subanswer": {"text": "The difference of squares is $a^2 - b^2=(ab)(a+b)$. The answer is $(ab)(a+b)$.", "value": 1}, "ost_step": {}}, "3": {"subquestion": "Now we can answer the question: What does the expression $(x-3)^2-(x-8)^2$ simplify to using the difference of squares formula?", "subanswer": {"text": "Using the difference of squares formula, we have $$(x-3)^2-(x-8)^2=((x-3)-(x-8))((x-3)+(x-8))=(5)(-1)=\\boxed{-5}.$$The answer is -5.", "value": 0.25}, "ost_step": {}}}, "rollout_id": 11}, {"trace": {"0": {"user_question": "What is the smallest real number $x$ in the domain of the function $$g(x) = \\sqrt{(x-3)^2-(x-8)^2}~?$$", "ost_step": {}}, "1": {"subquestion": "What expression is inside the square root in the function $g(x)$?", "subanswer": {"text": "It's $(x-3)^2-(x-8)^2$. The answer is $(x-3)^2-(x-8)^2$.", "value": 1}, "ost_step": {}}, "2": {"subquestion": "What is the difference of squares formula?", "subanswer": {"text": "The difference of squares is $a^2 - b^2=(ab)(a+b)$. The answer is $(ab)(a+b)$.", "value": 1}, "ost_step": {}}, "3": {"subquestion": "Now we can answer the question: What expression is obtained after applying the difference of squares formula?", "subanswer": {"text": "Applying the difference of squares formula to the expression yields $((x-3)-(x-8))((x-3)+(x-8))=(5)(-1)=(-5)$. The answer is (-5).", "value": 0.3125}, "ost_step": {}}}, "rollout_id": 11}, {"trace": {"0": {"user_question": "What is the smallest real number $x$ in the domain of the function $$g(x) = \\sqrt{(x-3)^2-(x-8)^2}~?$$", "ost_step": {}}, "1": {"subquestion": "What expression is inside the square root in the function $g(x)$?", "subanswer": {"text": "It's $(x-3)^2-(x-8)^2$. The answer is $(x-3)^2-(x-8)^2$.", "value": 1}, "ost_step": {}}, "2": {"subquestion": "What is the difference of squares formula?", "subanswer": {"text": "Let's think step by step. To find the difference of squares formula, we need to find a formula that allows us to easily compute the difference of two squares. We know that $a^2 - b^2 = (a + b)(ab)$. Therefore, the difference of squares formula is $\\boxed{(a+b)(ab)}$. The answer is: (a+b)(ab).", "value": 1}, "ost_step": {}, "direct_answer": {"text": "Let's think step by step. We can simplify the expression inside the square root using the difference of squares formula. Recall that the difference of squares formula states that $a^2-b^2=(a+b)(ab)$. So we can write the expression as follows: $\\begin{align*}\n&\\sqrt{(x-3)^2-(x-8)^2}\\\\\n=&\\qquad\\;\\sqrt{(x-3+x-8)((x-3)-(x-8))}\\\\\n=&\\qquad\\;\\sqrt{(2x-11)(5)}\n\\end{align*}$To eliminate the negative sign under the radical, we have that $2x-11 \\ge 0$, so that $x \\ge \\frac{11}{2}.$Therefore, the smallest real number $x$ in the domain of the function is $\\boxed{\\frac{11}{2}}$. The answer is: 11/2.", "value": 0.1875}}}, "rollout_id": 11}, {"trace": {"0": {"user_question": "What is the smallest real number $x$ in the domain of the function $$g(x) = \\sqrt{(x-3)^2-(x-8)^2}~?$$", "ost_step": {}}, "1": {"subquestion": "What expression is inside the square root in the function $g(x)$?", "subanswer": {"text": "It's $(x-3)^2-(x-8)^2$. The answer is $(x-3)^2-(x-8)^2$.", "value": 1}, "ost_step": {}}, "2": {"subquestion": "What is the difference of squares formula?", "subanswer": {"text": "Let's think step by step. To find the difference of squares formula, we need to find a formula that allows us to easily compute the difference of two squares. We know that $a^2 - b^2 = (a + b)(ab)$. Therefore, the difference of squares formula is $\\boxed{(a+b)(ab)}$. The answer is: (a+b)(ab).", "value": 1}, "ost_step": {}}, "3": {"subquestion": "Now we can answer the question: What expression is $(x-3)^2-(x-8)^2$ equivalent to using the difference of squares formula?", "subanswer": {"text": "Using the difference of squares formula, we have $(x-3)^2-(x-8)^2=(x-3+x-8)(x-3-x+8)=(-11)\\cdot 5=-55$. The answer is -55.", "value": 1}, "ost_step": {}}}, "rollout_id": 11}, {"trace": {"0": {"user_question": "What is the smallest real number $x$ in the domain of the function $$g(x) = \\sqrt{(x-3)^2-(x-8)^2}~?$$", "ost_step": {}}, "1": {"subquestion": "What expression is inside the square root in the function $g(x)$?", "subanswer": {"text": "Let's think step by step. To determine the value of $a$, let's expand the equation $f(a)=0$: $$x^2+x+\\frac{1}{16}=0$$We multiply each term in the left-hand side by $16$ to get rid of the fraction:$$16\\left(x^2+x+\\frac{1}{16}\\right)=16(0).$$Now we simplify the right hand side of the equation using the distributive property:$$16x^2+16x+1=0.$$Since this is a quadratic equation, it can be factored as follows: $$(4x+1)(4x+1)=0.$$This tells us that either $4x+1=0$, so $x=-\\frac{1}{4}$, or $4x+1=0$, so $x=-\\frac{1}{4}$. Therefore, our function $g(x)$ is equivalent to $\\frac{x^2}{1/16}=(x+1/4)^2.$Therefore, the expression inside the square root in the function $g(x)$ is $1/\\boxed{16}$. The answer is: 16.", "value": 1}, "ost_step": {}, "direct_answer": {"text": "To find the smallest real number $x$ in the domain of $g(x)$, we need to ensure that the value under the square root is non-negative because we're dealing with the square root of something. That means $(x-3)^2 - (x-8)^2 \\geq 0$. Simplifying this inequality, we get $(x-3+x-8)(x-3-x+8) \\geq 0$, which simplifies further to $(2x-11)(5) \\geq 0$. This means $2x-11 \\geq 0$, and thus $x \\geq 5.5$. Therefore, the smallest real number $x$ in the domain of the function $g(x)$ is $\\boxed{5.5}$. The answer is: 5.5.", "value": 0.3125}}}, "rollout_id": 1}, {"trace": {"0": {"user_question": "What is the smallest real number $x$ in the domain of the function $$g(x) = \\sqrt{(x-3)^2-(x-8)^2}~?$$", "ost_step": {}}, "1": {"subquestion": "What expression is inside the square root in the function $g(x)$?", "subanswer": {"text": "Let's think step by step. To determine the value of $a$, let's expand the equation $f(a)=0$: $$x^2+x+\\frac{1}{16}=0$$We multiply each term in the left-hand side by $16$ to get rid of the fraction:$$16\\left(x^2+x+\\frac{1}{16}\\right)=16(0).$$Now we simplify the right hand side of the equation using the distributive property:$$16x^2+16x+1=0.$$Since this is a quadratic equation, it can be factored as follows: $$(4x+1)(4x+1)=0.$$This tells us that either $4x+1=0$, so $x=-\\frac{1}{4}$, or $4x+1=0$, so $x=-\\frac{1}{4}$. Therefore, our function $g(x)$ is equivalent to $\\frac{x^2}{1/16}=(x+1/4)^2.$Therefore, the expression inside the square root in the function $g(x)$ is $1/\\boxed{16}$. The answer is: 16.", "value": 1}, "ost_step": {}}, "2": {"subquestion": "What condition must be met for the expression inside the square root to be non-negative?", "subanswer": {"text": "The condition for the expression inside the square root to be non-negative is $\\left(\\left|x-3\\right|-\\left|x-8\\right|\\right)\\geq 0$. The answer is $\\left(\\left|x-3\\right|-\\left|x-8\\right|\\right)\\geq 0$.", "value": 1}, "ost_step": {}, "direct_answer": {"text": "Let's think step by step. The expression inside the square root is $\\left|(x-3)-(x-8)\\right|=\\left|5\\right|=5$. Because $5$ is always nonnegative, any value of $x$ would make the expression inside the square root nonnegative. However, we need the denominator of the function to be nonzero, so $x\\neq 7.5$. The answer is: $\\boxed{0}$.", "value": 0.0625}}}, "rollout_id": 1}, {"trace": {"0": {"user_question": "What is the smallest real number $x$ in the domain of the function $$g(x) = \\sqrt{(x-3)^2-(x-8)^2}~?$$", "ost_step": {}}, "1": {"subquestion": "What expression is inside the square root in the function $g(x)$?", "subanswer": {"text": "Let's think step by step. To determine the value of $a$, let's expand the equation $f(a)=0$: $$x^2+x+\\frac{1}{16}=0$$We multiply each term in the left-hand side by $16$ to get rid of the fraction:$$16\\left(x^2+x+\\frac{1}{16}\\right)=16(0).$$Now we simplify the right hand side of the equation using the distributive property:$$16x^2+16x+1=0.$$Since this is a quadratic equation, it can be factored as follows: $$(4x+1)(4x+1)=0.$$This tells us that either $4x+1=0$, so $x=-\\frac{1}{4}$, or $4x+1=0$, so $x=-\\frac{1}{4}$. Therefore, our function $g(x)$ is equivalent to $\\frac{x^2}{1/16}=(x+1/4)^2.$Therefore, the expression inside the square root in the function $g(x)$ is $1/\\boxed{16}$. The answer is: 16.", "value": 1}, "ost_step": {}}, "2": {"subquestion": "What condition must be met for the expression inside the square root to be non-negative?", "subanswer": {"text": "The condition for the expression inside the square root to be non-negative is $\\left(\\left|x-3\\right|-\\left|x-8\\right|\\right)\\geq 0$. The answer is $\\left(\\left|x-3\\right|-\\left|x-8\\right|\\right)\\geq 0$.", "value": 1}, "ost_step": {}}, "3": {"subquestion": "What inequality does the condition reduce to?", "subanswer": {"text": "The absolute-value inequality reduces to the inequality $x<5$ The answer is x<5.", "value": 0.25}, "ost_step": {"1": "The answer is: -oo.5."}}}, "rollout_id": 1}, {"trace": {"0": {"user_question": "What is the smallest real number $x$ in the domain of the function $$g(x) = \\sqrt{(x-3)^2-(x-8)^2}~?$$", "ost_step": {}}, "1": {"subquestion": "What expression is inside the square root in the function $g(x)$?", "subanswer": {"text": "Let's think step by step. To determine the value of $a$, let's expand the equation $f(a)=0$: $$x^2+x+\\frac{1}{16}=0$$We multiply each term in the left-hand side by $16$ to get rid of the fraction:$$16\\left(x^2+x+\\frac{1}{16}\\right)=16(0).$$Now we simplify the right hand side of the equation using the distributive property:$$16x^2+16x+1=0.$$Since this is a quadratic equation, it can be factored as follows: $$(4x+1)(4x+1)=0.$$This tells us that either $4x+1=0$, so $x=-\\frac{1}{4}$, or $4x+1=0$, so $x=-\\frac{1}{4}$. Therefore, our function $g(x)$ is equivalent to $\\frac{x^2}{1/16}=(x+1/4)^2.$Therefore, the expression inside the square root in the function $g(x)$ is $1/\\boxed{16}$. The answer is: 16.", "value": 1}, "ost_step": {}}, "2": {"subquestion": "What condition must be met for the expression inside the square root to be non-negative?", "subanswer": {"text": "The condition for the expression inside the square root to be non-negative is $\\left(\\left|x-3\\right|-\\left|x-8\\right|\\right)\\geq 0$. The answer is $\\left(\\left|x-3\\right|-\\left|x-8\\right|\\right)\\geq 0$.", "value": 1}, "ost_step": {}}, "3": {"subquestion": "What inequality does the condition reduce to?", "subanswer": {"text": "The absolute-value inequality reduces to the inequality $x<5$ The answer is x<5.", "value": 0.25}, "ost_step": {}, "direct_answer": {"text": "Let's think step by step. Let's first analyze what the problem is asking for: we need to find the smallest real number $x$ such that $g(x)$ is defined. For $g(x)$ to be defined, the quantity $\\sqrt{(x-3)^2-(x-8)^2}$ must be a nonnegative real number. Since both terms inside the square root are squares, they are always nonnegative, but we still need to ensure that the difference of these two squares is also nonnegative. This leads us to the inequality $\\left(\\left|x-3\\right|-\\left|x-8\\right|\\right)\\geq 0$, because when you take the square root of a negative number, you get an imaginary number, and $g(x)$ needs to be a real number. The absolute-value inequality reduces to the inequality $x<5$. Now that we know this, we just need to pick any $x$ less than 5 and see if it makes the original expression under the square root non-negative. One option is $x=0$; in this case, the quantity $(x-3)^2-(x-8)^2$ becomes $(0-3)^2-(0-8)^2=(-", "value": 0.0625}}}, "rollout_id": 1}, {"trace": {"0": {"user_question": "What is the smallest real number $x$ in the domain of the function $$g(x) = \\sqrt{(x-3)^2-(x-8)^2}~?$$", "ost_step": {}}, "1": {"subquestion": "What expression is inside the square root in the function $g(x)$?", "subanswer": {"text": "Let's think step by step. To determine the value of $a$, let's expand the equation $f(a)=0$: $$x^2+x+\\frac{1}{16}=0$$We multiply each term in the left-hand side by $16$ to get rid of the fraction:$$16\\left(x^2+x+\\frac{1}{16}\\right)=16(0).$$Now we simplify the right hand side of the equation using the distributive property:$$16x^2+16x+1=0.$$Since this is a quadratic equation, it can be factored as follows: $$(4x+1)(4x+1)=0.$$This tells us that either $4x+1=0$, so $x=-\\frac{1}{4}$, or $4x+1=0$, so $x=-\\frac{1}{4}$. Therefore, our function $g(x)$ is equivalent to $\\frac{x^2}{1/16}=(x+1/4)^2.$Therefore, the expression inside the square root in the function $g(x)$ is $1/\\boxed{16}$. The answer is: 16.", "value": 1}, "ost_step": {}}, "2": {"subquestion": "What condition must be met for the expression inside the square root to be non-negative?", "subanswer": {"text": "The condition for the expression inside the square root to be non-negative is $\\left(\\left|x-3\\right|-\\left|x-8\\right|\\right)\\geq 0$. The answer is $\\left(\\left|x-3\\right|-\\left|x-8\\right|\\right)\\geq 0$.", "value": 1}, "ost_step": {}}, "3": {"subquestion": "What inequality does the condition reduce to?", "subanswer": {"text": "The absolute-value inequality reduces to the inequality $x<5$ The answer is x<5.", "value": 0.25}, "ost_step": {}}, "4": {"subquestion": "Now we can answer the question: What is the smallest real number $x$ in the domain of the function $g(x)$?", "subanswer": {"text": "The smallest real number $x$ in the domain of the function $g(x)$ is $5$. The answer is 5.", "value": 0.6875}, "ost_step": {}}}, "rollout_id": 1}, {"trace": {"0": {"user_question": "What is the smallest real number $x$ in the domain of the function $$g(x) = \\sqrt{(x-3)^2-(x-8)^2}~?$$", "ost_step": {}}, "1": {"subquestion": "What expression is inside the square root in the function $g(x)$?", "subanswer": {"text": "Let's think step by step. To determine the value of $a$, let's expand the equation $f(a)=0$: $$x^2+x+\\frac{1}{16}=0$$We multiply each term in the left-hand side by $16$ to get rid of the fraction:$$16\\left(x^2+x+\\frac{1}{16}\\right)=16(0).$$Now we simplify the right hand side of the equation using the distributive property:$$16x^2+16x+1=0.$$Since this is a quadratic equation, it can be factored as follows: $$(4x+1)(4x+1)=0.$$This tells us that either $4x+1=0$, so $x=-\\frac{1}{4}$, or $4x+1=0$, so $x=-\\frac{1}{4}$. Therefore, our function $g(x)$ is equivalent to $\\frac{x^2}{1/16}=(x+1/4)^2.$Therefore, the expression inside the square root in the function $g(x)$ is $1/\\boxed{16}$. The answer is: 16.", "value": 1}, "ost_step": {}}, "2": {"subquestion": "What condition must be met for the expression inside the square root to be non-negative?", "subanswer": {"text": "The condition for the expression inside the square root to be non-negative is $\\left(\\left|x-3\\right|-\\left|x-8\\right|\\right)\\geq 0$. The answer is $\\left(\\left|x-3\\right|-\\left|x-8\\right|\\right)\\geq 0$.", "value": 1}, "ost_step": {}}, "3": {"subquestion": "What inequality does the condition reduce to?", "subanswer": {"text": "The absolute-value inequality reduces to the inequality $x<5$ The answer is x<5.", "value": 0.25}, "ost_step": {}}, "4": {"subquestion": "Now we can answer the question: What is the smallest real number $x$ in the domain of the function $g(x)$?", "subanswer": {"text": "Since the smallest possible value of x is less than $5,$ this value of x must equal $5 - \\varepsilon,$ where $\\varepsilon$ is an arbitrary positive number approaching zero. Thus, when $\\varepsilon$ approaches zero, $5 - \\varepsilon$ also approaches $5,$ which is the smallest real number $x$ in the domain of the function. Therefore, the answer is $5-\\varepsilon$ . However, since you asked me to provide a numeric answer only, I'll ignore the variable $\\varepsilon$ and just say that the final answer is $5$. The answer is 5.", "value": 0.75}, "ost_step": {}}}, "rollout_id": 1}, {"trace": {"0": {"user_question": "What is the smallest real number $x$ in the domain of the function $$g(x) = \\sqrt{(x-3)^2-(x-8)^2}~?$$", "ost_step": {}}, "1": {"subquestion": "What expression is inside the square root in the function $g(x)$?", "subanswer": {"text": "Let's think step by step. To determine the value of $a$, let's expand the equation $f(a)=0$: $$x^2+x+\\frac{1}{16}=0$$We multiply each term in the left-hand side by $16$ to get rid of the fraction:$$16\\left(x^2+x+\\frac{1}{16}\\right)=16(0).$$Now we simplify the right hand side of the equation using the distributive property:$$16x^2+16x+1=0.$$Since this is a quadratic equation, it can be factored as follows: $$(4x+1)(4x+1)=0.$$This tells us that either $4x+1=0$, so $x=-\\frac{1}{4}$, or $4x+1=0$, so $x=-\\frac{1}{4}$. Therefore, our function $g(x)$ is equivalent to $\\frac{x^2}{1/16}=(x+1/4)^2.$Therefore, the expression inside the square root in the function $g(x)$ is $1/\\boxed{16}$. The answer is: 16.", "value": 1}, "ost_step": {}}, "2": {"subquestion": "What condition must be met for the expression inside the square root to be non-negative?", "subanswer": {"text": "The condition for the expression inside the square root to be non-negative is $\\left(\\left|x-3\\right|-\\left|x-8\\right|\\right)\\geq 0$. The answer is $\\left(\\left|x-3\\right|-\\left|x-8\\right|\\right)\\geq 0$.", "value": 1}, "ost_step": {}}, "3": {"subquestion": "Now we can answer the question: What is the smallest real number $x$ such that the expression inside the square root is nonnegative?", "subanswer": {"text": "The inequality holds if $x>8$, $x<3$, or $3\\le x\\le 8$. Thus the minimum value of $x$ satisfying the inequality is $\\boxed{3}.$ The answer is 3.", "value": 0.25}, "ost_step": {}}}, "rollout_id": 1}, {"trace": {"0": {"user_question": "What is the smallest real number $x$ in the domain of the function $$g(x) = \\sqrt{(x-3)^2-(x-8)^2}~?$$", "ost_step": {}}, "1": {"subquestion": "What are the expressions that represent the squares within the square root of the given expression for g(x)?", "subanswer": {"text": "They are $(x-3)^2$ and $(x-8)^2$. The answer is $(x-3)^2$ and $(x-8)^2$.", "value": 1}, "ost_step": {}, "direct_answer": {"text": "Let's think step by step. To begin solving this problem, we need to consider the conditions under which the expression inside the square root of the given function is non-negative. This leads us to the inequality $(x-3)^2 - (x-8)^2\\geq0$, as the square root of a negative number would result in an imaginary value, making it invalid for the function $g(x)$ when trying to find a real number $x$. Expanding both squares within the inequality, we get $$x^2-6x+9-x^2+16x-64\\geq0.$$ After combining like terms, we obtain $$10x-55\\geq0.$$\n\nSimplifying the inequality further gives us $$x\\geq\\frac{55}{10}=5.5.$$ However, we're interested in finding the smallest real number $x$ that satisfies this condition within the context of the given function. Therefore, the smallest real number $x$ that satisfies the inequality is $\\boxed{5.5}$ . The answer is: 5.5.", "value": 0.125}}}, "rollout_id": 2}, {"trace": {"0": {"user_question": "What is the smallest real number $x$ in the domain of the function $$g(x) = \\sqrt{(x-3)^2-(x-8)^2}~?$$", "ost_step": {}}, "1": {"subquestion": "What are the expressions that represent the squares within the square root of the given expression for g(x)?", "subanswer": {"text": "They are $(x-3)^2$ and $(x-8)^2$. The answer is $(x-3)^2$ and $(x-8)^2$.", "value": 1}, "ost_step": {}}, "2": {"subquestion": "Can we factor the expression inside the square root using the difference-of-squares formula?", "subanswer": {"text": "Yes, since we have $(x-3)^2-(x-8)^2=(x-3+x-8)(x-3-x+8)=(-11)(5)=(x-8)(x-3)$ but the difference of squares formula states that $a^2-b^2=(ab)(a+b)$ which would make our $a=x-8$ and $b=x-3$. The answer is yes.", "value": 1}, "ost_step": {}, "direct_answer": {"text": "Let's think step by step. Using the difference-of-squares formula, we can simplify the expression inside the square root as follows: \\begin{align*}\n(x-3)^2-(x-8)^2&amp;=(x-8)(x-3)\n\\end{align*}Since $x$ is in the domain of $g$, we know that $(x-8)(x-3)\\geq0$, so either both $x-8$ and $x-3$ are nonnegative, or both are nonpositive. If both are nonnegative, we get $x-8,x-3\\geq0$ or $x\\geq8$ and $x\\geq3$, so $x\\geq8$. If both are nonpositive, we get $x-8,x-3\\leq0$ or $x\\leq8$ and $x\\leq3$, so $x\\leq3$. Combining these inequalities, we see that the domain of $g(x)$ is $\\boxed{x\\in[3,8]}$. The answer is: [3,8].", "value": 0.0625}}}, "rollout_id": 8}, {"trace": {"0": {"user_question": "What is the smallest real number $x$ in the domain of the function $$g(x) = \\sqrt{(x-3)^2-(x-8)^2}~?$$", "ost_step": {}}, "1": {"subquestion": "What are the expressions that represent the squares within the square root of the given expression for g(x)?", "subanswer": {"text": "They are $(x-3)^2$ and $(x-8)^2$. The answer is $(x-3)^2$ and $(x-8)^2$.", "value": 1}, "ost_step": {}}, "2": {"subquestion": "Can we factor the expression inside the square root using the difference-of-squares formula?", "subanswer": {"text": "Yes, since we have $(x-3)^2-(x-8)^2=(x-3+x-8)(x-3-x+8)=(-11)(5)=(x-8)(x-3)$ but the difference of squares formula states that $a^2-b^2=(ab)(a+b)$ which would make our $a=x-8$ and $b=x-3$. The answer is yes.", "value": 1}, "ost_step": {}}, "3": {"subquestion": "Now we can answer the question: What is the expression inside the square root after factoring using the difference-of-squares formula?", "subanswer": {"text": "After applying the formula, we get $(x-8)(x-3)$. The answer is $(x-8)(x-3)$.", "value": 1}, "ost_step": {}}}, "rollout_id": 8}, {"trace": {"0": {"user_question": "What is the smallest real number $x$ in the domain of the function $$g(x) = \\sqrt{(x-3)^2-(x-8)^2}~?$$", "ost_step": {}}, "1": {"subquestion": "What are the expressions that represent the squares within the square root of the given expression for g(x)?", "subanswer": {"text": "Let's think step by step. To simplify the expression for $g(x)$, we need to evaluate the square roots first. The expression inside each square root is $81x^2 -64x +16$, so we get: \n\\begin{align*}\n    g(x)&= \\sqrt{81x^2-64x+16} \\\\\n&= \\sqrt{(9x-8)^2}\\\\\n&= 9x-8\\\\\n\\end{align*}\n\nTherefore, the simplified expression is $9x - 8$. The answer is: 9x-8.", "value": 1}, "ost_step": {"1": "To find the value of x that makes the expression undefined, we set it equal to zero and solve for x.", "2": "The expression becomes $(x-3)^2 - (x-8)^2 = 0.$"}, "direct_answer": {"text": "Let's think step by step. We first simplify the equation by expanding the squares: $(x^2 - 6x + 9) - (x^2 - 16x + 64) = 0.$ We combine like terms and get $10x - 55 = 0.$ We add $55$ to both sides and get $10x = 55.$ Now, we divide by $10$, so $x =\\boxed{11/2}$. The answer is: 11/2.", "value": 0.1875}}}, "rollout_id": 2}, {"trace": {"0": {"user_question": "What is the smallest real number $x$ in the domain of the function $$g(x) = \\sqrt{(x-3)^2-(x-8)^2}~?$$", "ost_step": {}}, "1": {"subquestion": "What are the expressions that represent the squares within the square root of the given expression for g(x)?", "subanswer": {"text": "Let's think step by step. To simplify the expression for $g(x)$, we need to evaluate the square roots first. The expression inside each square root is $81x^2 -64x +16$, so we get: \n\\begin{align*}\n    g(x)&= \\sqrt{81x^2-64x+16} \\\\\n&= \\sqrt{(9x-8)^2}\\\\\n&= 9x-8\\\\\n\\end{align*}\n\nTherefore, the simplified expression is $9x - 8$. The answer is: 9x-8.", "value": 1}, "ost_step": {"1": "To find the value of x that makes the expression undefined, we set it equal to zero and solve for x."}, "direct_answer": {"text": "Let's think step by step. Recall that the square root of a negative number is not defined in the real numbers. Therefore, we need to make sure that $(x-3)^2-(x-8)^2\\geq0$ so that we don't get any imaginary numbers when we take the square root. Let's expand and simplify the left-hand side of this inequality: $(x-3)^2-(x-8)^2=(x^2-6x+9)-(x^2-16x+64)=10x-55$. Now, let's set this less than or equal to 0 and solve for $x$: $10x-55\\leq0\\Rightarrow 10x\\leq55\\Rightarrow x\\leq\\frac{55}{10}=5.5$. Therefore, the largest possible value of $x$ is $5.5$, which is what we were looking for. The answer is: 5.5.", "value": 0.3125}}}, "rollout_id": 2}, {"trace": {"0": {"user_question": "What is the smallest real number $x$ in the domain of the function $$g(x) = \\sqrt{(x-3)^2-(x-8)^2}~?$$", "ost_step": {}}, "1": {"subquestion": "What are the expressions that represent the squares within the square root of the given expression for g(x)?", "subanswer": {"text": "Let's think step by step. To simplify the expression for $g(x)$, we need to evaluate the square roots first. The expression inside each square root is $81x^2 -64x +16$, so we get: \n\\begin{align*}\n    g(x)&= \\sqrt{81x^2-64x+16} \\\\\n&= \\sqrt{(9x-8)^2}\\\\\n&= 9x-8\\\\\n\\end{align*}\n\nTherefore, the simplified expression is $9x - 8$. The answer is: 9x-8.", "value": 1}, "ost_step": {}, "direct_answer": {"text": "To find the domain of this new function, we must ensure that $9x - 8 \\geq 0.$ Solving this inequality, we have $9x \\geq 8,$ which implies that $x \\geq 8/9$. However, since this problem asks us to find the smallest real number in the domain, the answer is $\\boxed{8/9}$.\nThe answer is: 8/9.", "value": 0.1875}}}, "rollout_id": 2}, {"trace": {"0": {"user_question": "Given a list of conditions, please answer the question. Condition 1:  There exists a function $g(x)$ defined as follows: $$g(x) = \\sqrt{(x-3)^2-(x-8)^2}.$$ Condition 2: We want to find the smallest real number in the domain of the function $g(x)$. Question: What is the smallest real number $x$ in the domain of $g(x)$?", "ost_step": {"1": "To find the domain of the function $g(x)$, we need to ensure that the expression inside the square root is nonnegative. That is, we need $(x-3)^2\\geq(x-8)^2$ or equivalently $(x-3+x-8)(x-3-x+8)\\geq0$, since it's a difference of squares, which simplifies to $(2x-11)(5)\\geq0$.", "2": "Solving the inequality, we see that $2x-11\\geq0$, so $2x\\geq11$, thus $x\\geq\\frac{11}{2}$.", "3": "Note that when $x<\\frac{11}{2}$, the inequality becomes false; hence, the domain of $g$ is $[\\frac{11}{2},\\infty).$"}, "direct_answer": {"text": "Let's think step by step. To find the domain of the function $g(x)$, we need to ensure that the expression inside the square root is nonnegative. This means $(x-3)^2\\geq(x-8)^2$, or equivalently $(x-3+x-8)(x-3-x+8)\\geq0$. Simplifying this expression, we get $2x-11\\geq0$. Solving the inequality, we find that $2x\\geq11$, which implies that $x\\geq\\frac{11}{2}$. We conclude that the domain of $g$ is $[\\frac{11}{2},\\infty)$. Thus, the smallest real number in the domain of $g(x)$ is $\\frac{11}{2}$. The answer is: \\frac{11}{2}.  . The answer is: \\frac{11}{2}.", "value": 0.6875}}}, "rollout_id": 12}, {"trace": {"0": {"user_question": "Given a list of conditions, please answer the question. Condition 1:  There exists a function $g(x)$ defined as follows: $$g(x) = \\sqrt{(x-3)^2-(x-8)^2}.$$ Condition 2: We want to find the smallest real number in the domain of the function $g(x)$. Question: What is the smallest real number $x$ in the domain of $g(x)$?", "ost_step": {"1": "To find the domain of the function $g(x)$, we need to ensure that the expression inside the square root is nonnegative. That is, we need $(x-3)^2\\geq(x-8)^2$ or equivalently $(x-3+x-8)(x-3-x+8)\\geq0$, since it's a difference of squares, which simplifies to $(2x-11)(5)\\geq0$.", "2": "Solving the inequality, we see that $2x-11\\geq0$, so $2x\\geq11$, thus $x\\geq\\frac{11}{2}$."}, "direct_answer": {"text": "Let's think step by step. Following the hint, we see that $(x-3)^2 - (x-8)^2 \\ge 0.$ Thus, we require the following inequality to hold: $(x-3)^2\\geq(x-8)^2$. Expanding both sides of the inequality yields \\begin{align*}\n(x-3)^2-(x-8)^2 &\\geq0\\\\\n(x^2-6x+9)-(x^2-16x+64)&\\geq0\\\\\nx^2-6x+9-x^2+16x-64&\\geq0\\\\\n10x-55&\\geq0\\\\\n10x&\\geq55\\\\\nx&\\geq\\frac{55}{10}=\\frac{11}{2}.\n\\end{align*}Therefore, the smallest value of $x$ in the domain of $g(x)$ is $\\boxed{\\frac{11}{2}}$. The answer is: \\frac{11}{2}.", "value": 0.375}}}, "rollout_id": 12}, {"trace": {"0": {"user_question": "Given a list of conditions, please answer the question. Condition 1:  There exists a function $g(x)$ defined as follows: $$g(x) = \\sqrt{(x-3)^2-(x-8)^2}.$$ Condition 2: We want to find the smallest real number in the domain of the function $g(x)$. Question: What is the smallest real number $x$ in the domain of $g(x)$?", "ost_step": {"1": "To find the domain of the function $g(x)$, we need to ensure that the expression inside the square root is nonnegative. That is, we need $(x-3)^2\\geq(x-8)^2$ or equivalently $(x-3+x-8)(x-3-x+8)\\geq0$, since it's a difference of squares, which simplifies to $(2x-11)(5)\\geq0$."}, "direct_answer": {"text": "Let's think step by step. In order for $g(x)$ to exist, the expression under the radical must be greater than or equal to zero. Using algebra, $(x-3)^2-(x-8)^2\\ge0$ becomes $(x-3+x-8)(x-3-x+8)\\ge0$, which simplifies to $(2x-11)(5)\\ge0$. Factoring out the common factor, we get $5(2x-11)\\ge0$. Dividing both sides by 5, we obtain $2x-11\\ge0$. Adding 11 to both sides yields $2x\\ge11$, so $x\\ge11/2=5.5$. Thus, the smallest real number in the domain of the function $g(x)$ is $\\boxed{5.5}$. The answer is: 5.5.", "value": 0.4375}}}, "rollout_id": 12}, {"trace": {"0": {"user_question": "Given a list of conditions, please answer the question. Condition 1:  There exists a function $g(x)$ defined as follows: $$g(x) = \\sqrt{(x-3)^2-(x-8)^2}.$$ Condition 2: We want to find the smallest real number in the domain of the function $g(x)$. Question: What is the smallest real number $x$ in the domain of $g(x)$?", "ost_step": {}, "direct_answer": {"text": "Let's think step by step. By factoring the square roots in the definition of $g(x)$, we obtain\n$$g(x)=\\sqrt{(x-3+x-8)(x-3-x+8)}=\\sqrt{(2x-11)(5)}=\\sqrt{10(2x-11)}.$$\nFor this expression to be defined, it must be nonnegative, so we require $2x-11 \\geq 0$, or $x \\geq \\frac{11}{2}$. Therefore, the smallest real number $x$ in the domain of $g(x)$ is $\\frac{11}{2}$. The answer is: 11/2.", "value": 0.375}}}, "rollout_id": 4}, {"trace": {"0": {"user_question": "Given a list of conditions, please answer the question. Condition 1:  There exists a function $g(x)$ defined as follows: $$g(x) = \\sqrt{(x-3)^2-(x-8)^2}.$$ Condition 2: We want to find the smallest real number in the domain of the function $g(x)$. Question: What is the smallest real number $x$ in the domain of $g(x)$?", "ost_step": {}}, "1": {"subquestion": "What does the expression inside the square root represent?", "subanswer": {"text": "This expression represents the difference of squares of the form $(a+b)(a-b)$, which simplifies to $a^2-b^2$. The answer is $(a+b)(a-b)$.", "value": 1}, "ost_step": {"1": "Therefore, the square root becomes $\\sqrt{(x-3+x-8)(x-3-x+8)}$, which further simplifies to $\\sqrt{(2x-11)(5)}$.", "2": "Since the expression inside the square root cannot be negative, we must have that both terms inside it are nonnegative."}, "direct_answer": {"text": "Let's think step by step. Let's first simplify the expression under the square root using the difference of squares identity. Given that $a^2 - b^2 = (a - b)(a + b),$ we have: $(x-3)^2 - (x-8)^2 = [(x-3) + (x-8)][(x-3) - (x-8)]$. This simplifies to: $(x-3)^2 - (x-8)^2 = [2x-11][5]$. Simplifying this, we get: $\\sqrt{(x-3)^2-(x-8)^2} = \\sqrt{[2x-11][5]}$. Now, since the expression inside the square root cannot be negative, we must have that both terms inside it are nonnegative. Thus, we must have that $2x-11\\geq0$ and $5\\geq0$. From the inequality $2x-11\\geq0$, we obtain that $x\\geq\\frac{11}{2}$. Hence, the smallest value of x satisfying this inequality is when x equals 5.5. Therefore, the answer is $\\boxed{5.5}", "value": 0.1875}}}, "rollout_id": 6}, {"trace": {"0": {"user_question": "Given a list of conditions, please answer the question. Condition 1:  There exists a function $g(x)$ defined as follows: $$g(x) = \\sqrt{(x-3)^2-(x-8)^2}.$$ Condition 2: We want to find the smallest real number in the domain of the function $g(x)$. Question: What is the smallest real number $x$ in the domain of $g(x)$?", "ost_step": {}}, "1": {"subquestion": "What does the expression inside the square root represent?", "subanswer": {"text": "This expression represents the difference of squares of the form $(a+b)(a-b)$, which simplifies to $a^2-b^2$. The answer is $(a+b)(a-b)$.", "value": 1}, "ost_step": {"1": "Therefore, the square root becomes $\\sqrt{(x-3+x-8)(x-3-x+8)}$, which further simplifies to $\\sqrt{(2x-11)(5)}$."}, "direct_answer": {"text": "Let's think step by step. To determine the smallest real number in the domain of $g(x)$, we must consider when the expression inside the square root is nonnegative. From condition 2, the expression inside the square root is $(2x-11)(5)$. It is nonnegative whenever both factors are nonnegative. Hence, it is sufficient to consider the inequalities $2x-11\\ge0$ and $5\\ge0$. Solving the first inequality yields $2x\\ge 11$, so $x\\ge \\frac{11}{2}=5.5$. Solving the second inequality yields no restriction on $x$ because any real number satisfies $5\\ge0$. Thus, the domain of $g(x)$ is the set of real numbers $x$ satisfying $x\\ge 5.5$. Since we seek the smallest such real number, the smallest real number in the domain of $g(x)$ is $\\boxed{5.5}$. The answer is: 5.5.", "value": 0.25}}}, "rollout_id": 6}, {"trace": {"0": {"user_question": "Given a list of conditions, please answer the question. Condition 1:  There exists a function $g(x)$ defined as follows: $$g(x) = \\sqrt{(x-3)^2-(x-8)^2}.$$ Condition 2: We want to find the smallest real number in the domain of the function $g(x)$. Question: What is the smallest real number $x$ in the domain of $g(x)$?", "ost_step": {}}, "1": {"subquestion": "What does the expression inside the square root represent?", "subanswer": {"text": "This expression represents the difference of squares of the form $(a+b)(a-b)$, which simplifies to $a^2-b^2$. The answer is $(a+b)(a-b)$.", "value": 1}, "ost_step": {}, "direct_answer": {"text": "To determine the domain of $g$, we first look at the expression inside the square root, $(x-3)^2 - (x-8)^2$. Using the hint provided, this expression can be written as $(x-3+x-8)(x-3-x+8)$, which further simplifies to $(2x-11)(5)$, or equivalently, $10x-55$. For the square root to yield a real value, this expression must be nonnegative, so $10x-55\\ge0$. Solving this inequality for $x$ yields $x\\ge\\frac{55}{10}$, or equivalently, $x\\ge\\frac{11}{2}$. Therefore, the domain of $g$ consists of all real numbers greater than or equal to $\\frac{11}{2}$. The smallest real number in the domain of $g$ is therefore $\\frac{11}{2}$ . The answer is: \\frac{11}{2}.", "value": 0.3125}}}, "rollout_id": 6}]