[{"trace": {"0": {"user_question": "A math club is having a bake sale as a fundraiser to raise money for an upcoming trip. They sell $54$ cookies at three for $\\$1$, and $20$ cupcakes at $\\$2$ each, and $35$ brownies at $\\$1$ each. If it cost the math club $\\$15$ to bake these items, what was their profit?", "ost_step": {"1": "The cost of baking $54$ cookies is $54 * 3 = $162$. The cost of baking $20$ cupcakes is $20 * $2 = $40$. The cost of baking $35$ brownies is $35 * $1 = $35$. Therefore, the total cost of baking these items is $162 + $40 + $35 = $275.", "2": "The price of one cookie is $1 * $2 = $2, and the price of one cupcake is $2 * $2 = $4. Therefore, the cost of baking each cookie is $2 + $4 = $6, and the cost of baking each cupcake is $2 * $2 = $4. Therefore, the total cost of baking these items is $6 * $4 = $24.", "3": "The cost of baking $54 cookies is $54 * $1 = $54. Therefore, the total cost of the bake sale is $54 + $54 = $108.", "4": "The total profit is the difference between the cost of baking the items and their prices, which is $108 - $54 = $54. Therefore, the answer is: $54$."}}}, "rollout_id": 5}, {"trace": {"0": {"user_question": "A math club is having a bake sale as a fundraiser to raise money for an upcoming trip. They sell $54$ cookies at three for $\\$1$, and $20$ cupcakes at $\\$2$ each, and $35$ brownies at $\\$1$ each. If it cost the math club $\\$15$ to bake these items, what was their profit?", "ost_step": {"1": "The cost of baking $54$ cookies is $54 * 3 = $162$. The cost of baking $20$ cupcakes is $20 * $2 = $40$. The cost of baking $35$ brownies is $35 * $1 = $35$. Therefore, the total cost of baking these items is $162 + $40 + $35 = $275.", "2": "The price of one cookie is $1 * $2 = $2, and the price of one cupcake is $2 * $2 = $4. Therefore, the cost of baking each cookie is $2 + $4 = $6, and the cost of baking each cupcake is $2 * $2 = $4. Therefore, the total cost of baking these items is $6 * $4 = $24.", "3": "The cost of baking $54 cookies is $54 * $1 = $54. Therefore, the total cost of the bake sale is $54 + $54 = $108."}, "direct_answer": {"text": "The math club made $108, so their profit is $108. The answer is: $108.", "value": 0.25}}}, "rollout_id": 5}, {"trace": {"0": {"user_question": "A math club is having a bake sale as a fundraiser to raise money for an upcoming trip. They sell $54$ cookies at three for $\\$1$, and $20$ cupcakes at $\\$2$ each, and $35$ brownies at $\\$1$ each. If it cost the math club $\\$15$ to bake these items, what was their profit?", "ost_step": {"1": "The cost of baking $54$ cookies is $54 * 3 = $162$. The cost of baking $20$ cupcakes is $20 * $2 = $40$. The cost of baking $35$ brownies is $35 * $1 = $35$. Therefore, the total cost of baking these items is $162 + $40 + $35 = $275.", "2": "The price of one cookie is $1 * $2 = $2, and the price of one cupcake is $2 * $2 = $4. Therefore, the cost of baking each cookie is $2 + $4 = $6, and the cost of baking each cupcake is $2 * $2 = $4. Therefore, the total cost of baking these items is $6 * $4 = $24."}, "direct_answer": {"text": "Let's think step by step. First, we find the cost of baking $54 cookies: $54 * 3 = $162$. Then, we find the cost of baking $20 cupcakes: $20 * $2 = $40$. Then, we find the cost of baking $35 brownies: $35 * $1 = $35$. Therefore, the total cost of baking these items is $162 + $40 + $35 = $275. The answer is: $275.", "value": 0.1875}}}, "rollout_id": 5}, {"trace": {"0": {"user_question": "A math club is having a bake sale as a fundraiser to raise money for an upcoming trip. They sell $54$ cookies at three for $\\$1$, and $20$ cupcakes at $\\$2$ each, and $35$ brownies at $\\$1$ each. If it cost the math club $\\$15$ to bake these items, what was their profit?", "ost_step": {"1": "The cost of baking $54$ cookies is $54 * 3 = $162$. The cost of baking $20$ cupcakes is $20 * $2 = $40$. The cost of baking $35$ brownies is $35 * $1 = $35$. Therefore, the total cost of baking these items is $162 + $40 + $35 = $275."}, "direct_answer": {"text": "Let's think step by step. The math club sells $54 cookies at $1 per cookie, so 54 cookies cost $54. The cost of baking $20 cupcakes is $20 * 2 = $40. The cost of baking $35 brownies is $35 * $1 = $35. Therefore, the total cost of baking these items is $54 + $40 + $35 = $119. The answer is: (119-54) = $65.", "value": 0.125}}}, "rollout_id": 2}, {"trace": {"0": {"user_question": "A math club is having a bake sale as a fundraiser to raise money for an upcoming trip. They sell $54$ cookies at three for $\\$1$, and $20$ cupcakes at $\\$2$ each, and $35$ brownies at $\\$1$ each. If it cost the math club $\\$15$ to bake these items, what was their profit?", "ost_step": {}, "direct_answer": {"text": "Let's think step by step. First, we need to calculate the total cost of all the items: $54 * 3 = $162$. Next, we need to calculate the total revenue: $20 * 4 = $80$. Finally, we need to subtract the cost from the revenue: $80 - $162 = $68$. The answer is: $68$. Therefore, the math club made $68$ in profit. The answer is: $68$.", "value": 0.0625}}}, "rollout_id": 0}, {"trace": {"0": {"user_question": "A math club is having a bake sale as a fundraiser to raise money for an upcoming trip. They sell $54$ cookies at three for $\\$1$, and $20$ cupcakes at $\\$2$ each, and $35$ brownies at $\\$1$ each. If it cost the math club $\\$15$ to bake these items, what was their profit?", "ost_step": {}}, "1": {"subquestion": "What is the cost per cookie?", "subanswer": {"text": "The cost per cookie is $1. The answer is 1.", "value": 1}, "ost_step": {}, "direct_answer": {"text": "Let's first find the total cost of baking the cookies: $54 * $1 = $\\boxed{$54}$. Then, find the total cost of baking the cupcakes: $20 * $2 = $\\boxed{$40}$. Lastly, find the total cost of baking the brownies: $35 * $1 = $\\boxed{$35}$. Therefore, the total cost of baking these items is $\\boxed{$54 + $40 + $35}$. To find the profit, subtract the total cost of baking these items from the total cost of selling them: $\\boxed{35 - \\boxed{$35}}$ = $\\boxed{1}$. The answer is: 1.", "value": 0.125}}}, "rollout_id": 0}, {"trace": {"0": {"user_question": "A math club is having a bake sale as a fundraiser to raise money for an upcoming trip. They sell $54$ cookies at three for $\\$1$, and $20$ cupcakes at $\\$2$ each, and $35$ brownies at $\\$1$ each. If it cost the math club $\\$15$ to bake these items, what was their profit?", "ost_step": {}}, "1": {"subquestion": "What is the cost per cookie?", "subanswer": {"text": "The cost per cookie is $1. The answer is 1.", "value": 1}, "ost_step": {}}, "2": {"subquestion": "What is the cost per cupcake?", "subanswer": {"text": "The cost per cupcake is $2. The answer is 2.", "value": 1}, "ost_step": {}, "direct_answer": {"text": "Let's think step by step. We know that $15$ was spent on baking the items, so the cost of baking is $15$. We can use algebra to find the cost of baking each item. We can bake $1$ cookie at a time, so the cost of baking each cookie is $1$. Similarly, we can bake each cupcake at a time, so the cost of baking each cupcake is $2$. Therefore, the cost of baking each item is $1+2=3$. The profit per cookie is $1-3=0$. The profit per cupcake is $1-2=1$. Therefore, the profit per item is $1+1=2$. The answer is: 2.", "value": 0.125}}}, "rollout_id": 0}, {"trace": {"0": {"user_question": "A math club is having a bake sale as a fundraiser to raise money for an upcoming trip. They sell $54$ cookies at three for $\\$1$, and $20$ cupcakes at $\\$2$ each, and $35$ brownies at $\\$1$ each. If it cost the math club $\\$15$ to bake these items, what was their profit?", "ost_step": {}}, "1": {"subquestion": "What is the cost per cookie?", "subanswer": {"text": "The cost per cookie is $1. The answer is 1.", "value": 1}, "ost_step": {}}, "2": {"subquestion": "What is the cost per cupcake?", "subanswer": {"text": "The cost per cupcake is $2. The answer is 2.", "value": 1}, "ost_step": {}}, "3": {"subquestion": "What is the cost per brownie?", "subanswer": {"text": "The cost per brownie is $1. The answer is 1.", "value": 1}, "ost_step": {"1": "The cost per item is $\\$1$."}, "direct_answer": {"text": "Let's think step by step. The cost of selling each cookie is $\\$2$, since it requires $2$ to make it. The cost of selling each cupcake is $1$. The cost of selling each brownie is $\\$1$, since it requires $1$ to make it. So, the total cost of selling these items is $\\boxed{54+20+35=$15}$. Therefore, the profit from selling these items is $\\boxed{15}$. The answer is: (15).", "value": 0.0625}}}, "rollout_id": 0}, {"trace": {"0": {"user_question": "A math club is having a bake sale as a fundraiser to raise money for an upcoming trip. They sell $54$ cookies at three for $\\$1$, and $20$ cupcakes at $\\$2$ each, and $35$ brownies at $\\$1$ each. If it cost the math club $\\$15$ to bake these items, what was their profit?", "ost_step": {}}, "1": {"subquestion": "What is the cost per cookie?", "subanswer": {"text": "The cost per cookie is $1. The answer is 1.", "value": 1}, "ost_step": {}}, "2": {"subquestion": "What is the cost per cupcake?", "subanswer": {"text": "The cost per cupcake is $2. The answer is 2.", "value": 1}, "ost_step": {}}, "3": {"subquestion": "What is the cost per brownie?", "subanswer": {"text": "The cost per brownie is $1. The answer is 1.", "value": 1}, "ost_step": {}, "direct_answer": {"text": "Let's think step by step. The cost of baking the cookies is $1, so the cost of $1 cookie is $\\boxed{1}$. The cost of baking the cupcakes is $2, so the cost of $2 cupcakes is $4. The cost of baking the brownies is $1, so the cost of $1 brownie is $1. Therefore, the total cost of baking all the items is $4 + $4 + $1 = $9. The answer is: 9.", "value": 0.125}}}, "rollout_id": 0}, {"trace": {"0": {"user_question": "A math club is having a bake sale as a fundraiser to raise money for an upcoming trip. They sell $54$ cookies at three for $\\$1$, and $20$ cupcakes at $\\$2$ each, and $35$ brownies at $\\$1$ each. If it cost the math club $\\$15$ to bake these items, what was their profit?", "ost_step": {}}, "1": {"subquestion": "What is the cost per cookie?", "subanswer": {"text": "The cost per cookie is $1. The answer is 1.", "value": 1}, "ost_step": {}}, "2": {"subquestion": "What is the cost per cupcake?", "subanswer": {"text": "The cost per cupcake is $2. The answer is 2.", "value": 1}, "ost_step": {}}, "3": {"subquestion": "What is the cost per brownie?", "subanswer": {"text": "The cost per brownie is $1. The answer is 1.", "value": 1}, "ost_step": {}}, "4": {"subquestion": "Now we can answer the question: What was their total cost to bake these items?", "subanswer": {"text": "The total cost to bake these items is $54 + $20 + $35 = $109. The answer is 109.", "value": 0.1875}, "ost_step": {}}}, "rollout_id": 0}, {"trace": {"0": {"user_question": "A math club is having a bake sale as a fundraiser to raise money for an upcoming trip. They sell $54$ cookies at three for $\\$1$, and $20$ cupcakes at $\\$2$ each, and $35$ brownies at $\\$1$ each. If it cost the math club $\\$15$ to bake these items, what was their profit?", "ost_step": {}}, "1": {"subquestion": "What is the cost per cookie?", "subanswer": {"text": "Let's think step by step. First, we can solve for the cost of cookies by finding the total cost of selling $54$ cookies at $\\$1$ each. Cookies sell for $\\boxed{3}$ each, so the total cost of selling $54$ cookies is $\\boxed{54*3} = $162$. Then, we can use the formula $C(x,y) = -y + (x+y)^2 + (y+x)^2 - 2x*y + b$ to solve for the cost of each cookie, where $b$ is the selling price of the brownie ($1). The cost per cookie is $\\boxed{-(b+54)}$. The answer is: $\\boxed{-($54+54)}$.", "value": 1}, "ost_step": {}, "direct_answer": {"text": "Let's calculate the cost of each item sold. Each cookie sells for $\\boxed{3}$ each, so the cost of each cookie is $9$. The brownie sells for $\\boxed{1}$ each, so the cost of each brownie is $1$. Therefore, the cost of each cookie is $9$ and the cost of each brownie is $1$. The total cost of selling these items is $9 + $1 + $54 + $54 + $54 = $162$. The profit of selling these items is $162 - $162 = $0$. Therefore, the answer is: $0$.", "value": 0.0625}}}, "rollout_id": 8}, {"trace": {"0": {"user_question": "A math club is having a bake sale as a fundraiser to raise money for an upcoming trip. They sell $54$ cookies at three for $\\$1$, and $20$ cupcakes at $\\$2$ each, and $35$ brownies at $\\$1$ each. If it cost the math club $\\$15$ to bake these items, what was their profit?", "ost_step": {}}, "1": {"subquestion": "What is the cost per cookie?", "subanswer": {"text": "Let's think step by step. First, we can solve for the cost of cookies by finding the total cost of selling $54$ cookies at $\\$1$ each. Cookies sell for $\\boxed{3}$ each, so the total cost of selling $54$ cookies is $\\boxed{54*3} = $162$. Then, we can use the formula $C(x,y) = -y + (x+y)^2 + (y+x)^2 - 2x*y + b$ to solve for the cost of each cookie, where $b$ is the selling price of the brownie ($1). The cost per cookie is $\\boxed{-(b+54)}$. The answer is: $\\boxed{-($54+54)}$.", "value": 1}, "ost_step": {}}, "2": {"subquestion": "Now we can answer the question: \"What was their profit?\".", "subanswer": {"text": "The profit can be calculated by subtracting the total cost from the total revenue, which is $\\boxed{$15 - $54 - $20 - $35 = $1}$. The answer is $1$.", "value": 0.125}, "ost_step": {}}}, "rollout_id": 8}, {"trace": {"0": {"user_question": "A math club is having a bake sale as a fundraiser to raise money for an upcoming trip. They sell $54$ cookies at three for $\\$1$, and $20$ cupcakes at $\\$2$ each, and $35$ brownies at $\\$1$ each. If it cost the math club $\\$15$ to bake these items, what was their profit?", "ost_step": {}}, "1": {"subquestion": "What is the cost per cookie?", "subanswer": {"text": "Let's think step by step. First, we can solve for the cost of cookies by finding the total cost of selling $54$ cookies at $\\$1$ each. Cookies sell for $\\boxed{3}$ each, so the total cost of selling $54$ cookies is $\\boxed{54*3} = $162$. Then, we can use the formula $C(x,y) = -y + (x+y)^2 + (y+x)^2 - 2x*y + b$ to solve for the cost of each cookie, where $b$ is the selling price of the brownie ($1). The cost per cookie is $\\boxed{-(b+54)}$. The answer is: $\\boxed{-($54+54)}$.", "value": 1}, "ost_step": {}}, "2": {"subquestion": "Now we can answer the question: What was their profit?", "subanswer": {"text": "The profit from selling cookies is $\\boxed{54*3 - ($54+54)}$. The answer is $\\boxed{($-81)}$.", "value": 0.0625}, "ost_step": {}}}, "rollout_id": 8}, {"trace": {"0": {"user_question": "A math club is having a bake sale as a fundraiser to raise money for an upcoming trip. They sell $54$ cookies at three for $\\$1$, and $20$ cupcakes at $\\$2$ each, and $35$ brownies at $\\$1$ each. If it cost the math club $\\$15$ to bake these items, what was their profit?", "ost_step": {}}, "1": {"subquestion": "What is the cost of selling $\\boxed{20}$ cupcakes at $\\$2$ each?", "subanswer": {"text": "The cost of selling $20$ cupcakes is $2$. The answer is $2$.", "value": 1}, "ost_step": {"1": "The cost of selling $3$ cookies is $3$.", "2": "The cost of selling $20$ cupcakes is $10$."}, "direct_answer": {"text": "Let's think step by step. To find the cost of $1$ cookie, we use the formula $C = Q + R$. In this case, $C$ is the total cost, $C = (Q+R)$, where $Q$ is the cost of selling $3$ cookies and $R$ is the cost of selling $10$ cupcakes. So, the cost of selling $3$ cookies is $3$ and the cost of selling $10$ cupcakes is $10$. Therefore, the total cost of selling $3$ cookies and $10$ cupcakes is $23$. Since the cost of selling $3$ cookies is $3$, the profit is $23-$3 = $20$. The answer is: (20,-3).", "value": 0.0625}}}, "rollout_id": 6}, {"trace": {"0": {"user_question": "A math club is having a bake sale as a fundraiser to raise money for an upcoming trip. They sell $54$ cookies at three for $\\$1$, and $20$ cupcakes at $\\$2$ each, and $35$ brownies at $\\$1$ each. If it cost the math club $\\$15$ to bake these items, what was their profit?", "ost_step": {}}, "1": {"subquestion": "What is the cost of selling $\\boxed{20}$ cupcakes at $\\$2$ each?", "subanswer": {"text": "The cost of selling $20$ cupcakes is $2$. The answer is $2$.", "value": 1}, "ost_step": {"1": "The cost of selling $3$ cookies is $3$."}, "direct_answer": {"text": "Let's think step by step. They sold $\\boxed{54}$ cookies at $\\$1$ each for a total of $54$ ($54 = $1 * $3$). They sold $\\boxed{20}$ cupcakes at $\\$2$ each for a total of $80$ ($80 = $2 * $40$). And they sold $\\boxed{35}$ brownies at $\\$1$ each for a total of $350$ ($350 = $1 * $350$). The math club spent $15$ to bake these items, so the total cost of baking these items is $15 + $3 + $350 = $$15 + $4 = $19$. Therefore, their profit is $54 - $19 = $35. The answer is: $35$.", "value": 0.125}}}, "rollout_id": 6}, {"trace": {"0": {"user_question": "A math club is having a bake sale as a fundraiser to raise money for an upcoming trip. They sell $54$ cookies at three for $\\$1$, and $20$ cupcakes at $\\$2$ each, and $35$ brownies at $\\$1$ each. If it cost the math club $\\$15$ to bake these items, what was their profit?", "ost_step": {}}, "1": {"subquestion": "What is the cost of selling $\\boxed{20}$ cupcakes at $\\$2$ each?", "subanswer": {"text": "The cost of selling $20$ cupcakes is $2$. The answer is $2$.", "value": 1}, "ost_step": {}, "direct_answer": {"text": "Let's think step by step. They have $54 \\times 3$ cookies sold at $1$. They have $20 \\times 2$ cupcakes sold at $2$, which adds up to $40$ sold. They have $35 \\times 1$ brownies sold at $1$. So, they have $1 + (2*1) + (1*2) + (1*1) = $4$ sold. Therefore, their profit is $4$. The answer is: 4.", "value": 0.125}}}, "rollout_id": 3}, {"trace": {"0": {"user_question": "A math club is having a bake sale as a fundraiser to raise money for an upcoming trip. They sell $54$ cookies at three for $\\$1$, and $20$ cupcakes at $\\$2$ each, and $35$ brownies at $\\$1$ each. If it cost the math club $\\$15$ to bake these items, what was their profit?", "ost_step": {}}, "1": {"subquestion": "What is the cost of selling $\\boxed{20}$ cupcakes at $\\$2$ each?", "subanswer": {"text": "The cost of selling $20$ cupcakes is $2$. The answer is $2$.", "value": 1}, "ost_step": {}}, "2": {"subquestion": "What is the cost of selling $\\boxed{35}$ brownies at $\\$1$ each?", "subanswer": {"text": "The cost of selling $35$ brownies is $35$. The answer is $35$.", "value": 1}, "ost_step": {}, "direct_answer": {"text": "Let's think step by step. First, we find the cost of selling the $20$ cookies: $2\\times(20) = $40$. Second, we find the cost of selling the $35$ brownies: $35\\times(2) = $70$. Then, we find the profit by subtracting the cost from the sale price: $54-40 = $14$. Finally, we multiply the profit by $15 to get their total profit: $14\\times$15 = $<<14*15=120>>120$. Therefore, the answer is: $120$.", "value": 0.0625}}}, "rollout_id": 15}, {"trace": {"0": {"user_question": "A math club is having a bake sale as a fundraiser to raise money for an upcoming trip. They sell $54$ cookies at three for $\\$1$, and $20$ cupcakes at $\\$2$ each, and $35$ brownies at $\\$1$ each. If it cost the math club $\\$15$ to bake these items, what was their profit?", "ost_step": {}}, "1": {"subquestion": "What is the cost of selling $\\boxed{20}$ cupcakes at $\\$2$ each?", "subanswer": {"text": "The cost of selling $20$ cupcakes is $2$. The answer is $2$.", "value": 1}, "ost_step": {}}, "2": {"subquestion": "What is the cost of selling $\\boxed{35}$ brownies at $\\$1$ each?", "subanswer": {"text": "The cost of selling $35$ brownies is $35$. The answer is $35$.", "value": 1}, "ost_step": {}}, "3": {"subquestion": "What is the cost of baking $54$ cookies at $\\$1$ each?", "subanswer": {"text": "The cost of baking $54$ cookies is $54$. The answer is $54$.", "value": 1.0}, "ost_step": {}, "direct_answer": {"text": "Let's think step by step. The cost of baking cookies is $54$. So, the cost of selling them is $1 + $54 = $55$. The cost of selling $20$ cupcakes is $20$. The cost of selling $35$ brownies is $35$. The cost of baking $54 cookies is $54$. So, the cost of selling $54 cookies is $54$. Therefore, the math club's profit is $54$. The answer is: $54$.", "value": 0.1875}}}, "rollout_id": 15}, {"trace": {"0": {"user_question": "A math club is having a bake sale as a fundraiser to raise money for an upcoming trip. They sell $54$ cookies at three for $\\$1$, and $20$ cupcakes at $\\$2$ each, and $35$ brownies at $\\$1$ each. If it cost the math club $\\$15$ to bake these items, what was their profit?", "ost_step": {}}, "1": {"subquestion": "What is the cost of selling $\\boxed{20}$ cupcakes at $\\$2$ each?", "subanswer": {"text": "The cost of selling $20$ cupcakes is $2$. The answer is $2$.", "value": 1}, "ost_step": {}}, "2": {"subquestion": "What is the cost of selling $\\boxed{35}$ brownies at $\\$1$ each?", "subanswer": {"text": "The cost of selling $35$ brownies is $35$. The answer is $35$.", "value": 1}, "ost_step": {}}, "3": {"subquestion": "What is the cost of baking $54$ cookies at $\\$1$ each?", "subanswer": {"text": "The cost of baking $54$ cookies is $54$. The answer is $54$.", "value": 1.0}, "ost_step": {}}, "4": {"subquestion": "What is the cost of baking $100$ cookies?", "subanswer": {"text": "Baking $100$ cookies would cost $100$. The answer is $100$.", "value": 0.9375}, "ost_step": {}, "direct_answer": {"text": "Let's think step by step. Baking $100$ cookies costs $100$. Selling them for $\\boxed{1}$ each means they cost $1 each. Baking $100$ of them costs $100$. So, their cost of baking $100$ cookies is $100$. Baking $100$ of $\\boxed{20}$ cupcakes costs $100$. Baking $100$ of $\\boxed{35}$ brownies costs $100$. Baking $100$ of $54$ cookies costs $100$. Therefore, the cost of baking $100$ cookies is $100$. The answer is: $100$.", "value": 0.375}}}, "rollout_id": 15}, {"trace": {"0": {"user_question": "A math club is having a bake sale as a fundraiser to raise money for an upcoming trip. They sell $54$ cookies at three for $\\$1$, and $20$ cupcakes at $\\$2$ each, and $35$ brownies at $\\$1$ each. If it cost the math club $\\$15$ to bake these items, what was their profit?", "ost_step": {}}, "1": {"subquestion": "What is the cost of selling $\\boxed{20}$ cupcakes at $\\$2$ each?", "subanswer": {"text": "The cost of selling $20$ cupcakes is $2$. The answer is $2$.", "value": 1}, "ost_step": {}}, "2": {"subquestion": "What is the cost of selling $\\boxed{35}$ brownies at $\\$1$ each?", "subanswer": {"text": "The cost of selling $35$ brownies is $35$. The answer is $35$.", "value": 1}, "ost_step": {}}, "3": {"subquestion": "What is the cost of baking $54$ cookies at $\\$1$ each?", "subanswer": {"text": "The cost of baking $54$ cookies is $54$. The answer is $54$.", "value": 1.0}, "ost_step": {}}, "4": {"subquestion": "Now we can answer the question: What was the profit of the math club?", "subanswer": {"text": "The profit of the math club is $15$. The answer is $15$.", "value": 0.5}, "ost_step": {}}}, "rollout_id": 15}, {"trace": {"0": {"user_question": "A math club is having a bake sale as a fundraiser to raise money for an upcoming trip. They sell $54$ cookies at three for $\\$1$, and $20$ cupcakes at $\\$2$ each, and $35$ brownies at $\\$1$ each. If it cost the math club $\\$15$ to bake these items, what was their profit?", "ost_step": {}}, "1": {"subquestion": "What is the cost of selling $\\boxed{20}$ cupcakes at $\\$2$ each?", "subanswer": {"text": "The cost of selling $20$ cupcakes is $2$. The answer is $2$.", "value": 1}, "ost_step": {}}, "2": {"subquestion": "What is the cost of selling $\\boxed{35}$ brownies at $\\$1$ each?", "subanswer": {"text": "The cost of selling $35$ brownies is $35$. The answer is $35$.", "value": 1}, "ost_step": {}}, "3": {"subquestion": "Now we can answer the question: What was the total cost of the bake sale?", "subanswer": {"text": "The total cost of the bake sale is $54 + $20 + $35 = $99. The answer is $99.", "value": 0.25}, "ost_step": {}}}, "rollout_id": 15}, {"trace": {"0": {"user_question": "A math club is having a bake sale as a fundraiser to raise money for an upcoming trip. They sell $54$ cookies at three for $\\$1$, and $20$ cupcakes at $\\$2$ each, and $35$ brownies at $\\$1$ each. If it cost the math club $\\$15$ to bake these items, what was their profit?", "ost_step": {}}, "1": {"subquestion": "What is the cost of selling $\\boxed{20}$ cupcakes at $\\$2$ each?", "subanswer": {"text": "The cost of selling $20$ cupcakes is $2$. The answer is $2$.", "value": 1}, "ost_step": {}}, "2": {"subquestion": "What is the cost of selling $\\boxed{15}$ brownies at $\\$1$ each?", "subanswer": {"text": "The cost of selling $15$ brownies is $1$. The answer is $1$.", "value": 1}, "ost_step": {}, "direct_answer": {"text": "Let's use the information given in the hint. For $\\boxed{20}$ cupcakes at $2$ each, the cost of selling $\\boxed{20}$ is $2*15 = $30$. For $\\boxed{15}$ brownies at $1$ each, the cost of selling $\\boxed{15}$ is $15$. Therefore, the math club's profit for $\\$15$ is $15 - $30 = $15$. The answer is: $15$.", "value": 0.1875}}}, "rollout_id": 10}, {"trace": {"0": {"user_question": "A math club is having a bake sale as a fundraiser to raise money for an upcoming trip. They sell $54$ cookies at three for $\\$1$, and $20$ cupcakes at $\\$2$ each, and $35$ brownies at $\\$1$ each. If it cost the math club $\\$15$ to bake these items, what was their profit?", "ost_step": {}}, "1": {"subquestion": "What is the cost of selling $\\boxed{20}$ cupcakes at $\\$2$ each?", "subanswer": {"text": "The cost of selling $20$ cupcakes is $2$. The answer is $2$.", "value": 1}, "ost_step": {}}, "2": {"subquestion": "What is the cost of selling $\\boxed{15}$ brownies at $\\$1$ each?", "subanswer": {"text": "The cost of selling $15$ brownies is $1$. The answer is $1$.", "value": 1}, "ost_step": {}}, "3": {"subquestion": "Now we can answer the question: What was their profit?", "subanswer": {"text": "The profit is $15$. The answer is 15.", "value": 0.25}, "ost_step": {}}}, "rollout_id": 10}, {"trace": {"0": {"user_question": "A math club is having a bake sale as a fundraiser to raise money for an upcoming trip. They sell $54$ cookies at three for $\\$1$, and $20$ cupcakes at $\\$2$ each, and $35$ brownies at $\\$1$ each. If it cost the math club $\\$15$ to bake these items, what was their profit?", "ost_step": {}}, "1": {"subquestion": "What is the cost of selling $\\boxed{20}$ cupcakes at $\\$2$ each?", "subanswer": {"text": "The cost of selling $20$ cupcakes is $2$. The answer is $2$.", "value": 1}, "ost_step": {}}, "2": {"subquestion": "What is the cost of selling $\\boxed{15}$ brownies at $\\$1$ each?", "subanswer": {"text": "The cost of selling $15$ brownies is $1$. The answer is $1$.", "value": 1}, "ost_step": {}}, "3": {"subquestion": "Now we can answer the question: How much did the math club make on this fundraiser?", "subanswer": {"text": "To calculate the profit, we add the cost of baking the items ($15) to the revenue of selling them ($54 + $2 + $20 + $1 = $91). The answer is $91$.", "value": 0.0625}, "ost_step": {}}}, "rollout_id": 10}, {"trace": {"0": {"user_question": "A math club is having a bake sale as a fundraiser to raise money for an upcoming trip. They sell $54$ cookies at three for $\\$1$, and $20$ cupcakes at $\\$2$ each, and $35$ brownies at $\\$1$ each. If it cost the math club $\\$15$ to bake these items, what was their profit?", "ost_step": {}}, "1": {"subquestion": "What is the cost of selling $\\boxed{20}$ cupcakes at $\\$2$ each?", "subanswer": {"text": "The cost of selling $20$ cupcakes is $2$. The answer is $2$.", "value": 1}, "ost_step": {}}, "2": {"subquestion": "What is the cost of selling $\\boxed{15}$ brownies at $\\$1$ each?", "subanswer": {"text": "Let's think step by step. The cost of selling $20$ cupcakes is $20*\\$2 = $40$. The cost of selling $\\boxed{20}$ cookies is $20*\\$1 = $20$. The cost of selling $35$ brownies is $35*\\$1 = $35$. Therefore, the cost of selling $\\boxed{15}$ brownies is $35+20 = $55$. The answer is: $55$.", "value": 1}, "ost_step": {}, "direct_answer": {"text": "Let's think step by step. We want to find out how much they made selling each type of cookie, cupcake, and brownie. First, we can find the cost of selling $1$ cookie and $2$ cupcake. To find the cost of selling $20$ brownie, we'll use the fact that it costs $\\$2$ to bake $1$ brownie. Therefore, the cost of selling $\\boxed{20}$ brownie is $\\boxed{20}$*2 = $40$. The answer is: $40$.\n\nNext, we'll find the cost of selling $1$ cupcake, $2$ cookie, and $3$ brownie. Let's start with $1$ cupcake. To bake $1$ cupcake, it costs $\\$2$. Therefore, the cost of baking $1$ cupcake is $2$.\n\nNext, let's find the cost of selling $2$ cookie. Baking $2$ cookies costs $\\$4$. Therefore, the cost of baking $2$ cookie is $4$.\n\nFinally, let's find the cost of baking $3$", "value": 0.125}}}, "rollout_id": 10}, {"trace": {"0": {"user_question": "A math club is having a bake sale as a fundraiser to raise money for an upcoming trip. They sell $54$ cookies at three for $\\$1$, and $20$ cupcakes at $\\$2$ each, and $35$ brownies at $\\$1$ each. If it cost the math club $\\$15$ to bake these items, what was their profit?", "ost_step": {}}, "1": {"subquestion": "What is the cost of selling $\\boxed{20}$ cupcakes at $\\$2$ each?", "subanswer": {"text": "The cost of selling $20$ cupcakes is $2$. The answer is $2$.", "value": 1}, "ost_step": {}}, "2": {"subquestion": "What is the cost of selling $\\boxed{15}$ brownies at $\\$1$ each?", "subanswer": {"text": "Let's think step by step. The cost of selling $20$ cupcakes is $20*\\$2 = $40$. The cost of selling $\\boxed{20}$ cookies is $20*\\$1 = $20$. The cost of selling $35$ brownies is $35*\\$1 = $35$. Therefore, the cost of selling $\\boxed{15}$ brownies is $35+20 = $55$. The answer is: $55$.", "value": 1}, "ost_step": {}}, "3": {"subquestion": "Now we can answer the question: What was the profit from selling these items?", "subanswer": {"text": "Let's think step by step. The profit from selling $20*\\$2 cookies is $20*\\$2 - $20*\\$1 = $20$. The profit from selling $20*\\$2 brownies is $20*\\$2 - $20*\\$1 = $20$. The profit from selling $35*\\$1 cookies is $35*$1 - $35*$1 = $0$. The profit from selling $35*$1 brownies is $35*$1 - $35*$1 = $0$. Therefore, the profit from selling $15*\\$1 cookies is $20+$20 = $60$. The profit from selling $15*$2 brownies is $20+$20 = $40$. The answer is: $60$.", "value": 0.125}, "ost_step": {}}}, "rollout_id": 10}, {"trace": {"0": {"user_question": "A math club is having a bake sale as a fundraiser to raise money for an upcoming trip. They sell $54$ cookies at three for $\\$1$, and $20$ cupcakes at $\\$2$ each, and $35$ brownies at $\\$1$ each. If it cost the math club $\\$15$ to bake these items, what was their profit?", "ost_step": {}}, "1": {"subquestion": "What is the cost of selling $\\boxed{20}$ cupcakes at $\\$2$ each?", "subanswer": {"text": "The cost of selling $20$ cupcakes is $2$. The answer is $2$.", "value": 1}, "ost_step": {}}, "2": {"subquestion": "What is the cost of selling $\\boxed{15}$ brownies at $\\$1$ each?", "subanswer": {"text": "Let's think step by step. The cost of selling $20$ cupcakes is $20*\\$2 = $40$. The cost of selling $\\boxed{20}$ cookies is $20*\\$1 = $20$. The cost of selling $35$ brownies is $35*\\$1 = $35$. Therefore, the cost of selling $\\boxed{15}$ brownies is $35+20 = $55$. The answer is: $55$.", "value": 1}, "ost_step": {}}, "3": {"subquestion": "Now we can answer the question: What is their profit?", "subanswer": {"text": "$55$ + $20$ + $35$ = $100$. The answer is $100$.", "value": 0.125}, "ost_step": {}}}, "rollout_id": 10}, {"trace": {"0": {"user_question": "Given a list of conditions, please answer the question. Condition 1: $1/4$; please answer the question. $9$; please answer the question.", "ost_step": {"1": "$1/4$ is equivalent to $1/2$. Therefore, $(1/2) = 9$.", "2": "The image of $9$ is $(9,4)$. Therefore, the answer is $(-9,4)$."}}}, "rollout_id": 1}, {"trace": {"0": {"user_question": "Given a list of conditions, please answer the question. Condition 1: $1/4$; please answer the question. $9$; please answer the question.", "ost_step": {"1": "$1/4$ is equivalent to $1/2$. Therefore, $(1/2) = 9$."}, "direct_answer": {"text": "Let's think step by step. Given a list of conditions: $1/4 = 1/2$. Then, multiplying $1/4$ and $1/2$ gives $\\boxed{1}$. The answer is: 1.", "value": 0.375}}}, "rollout_id": 1}, {"trace": {"0": {"user_question": "Given a list of conditions, please answer the question. Condition 1: $1/4$; please answer the question. $9$; please answer the question.", "ost_step": {}, "direct_answer": {"text": "$9$ is the smallest integer that satisfies both $(1/4=1)$ and $9$. Therefore, the answer is: $9$.", "value": 0.1875}}}, "rollout_id": 1}, {"trace": {"0": {"user_question": "Given a list of conditions, please answer the question. Condition 1: $1/4$; please answer the question. $9$; please answer the question.", "ost_step": {}}, "1": {"subquestion": "What is the value of $9$?", "subanswer": {"text": "$9 = 2$.", "value": 1}, "ost_step": {"1": "$1/4$ is equal to $(1-3)/4$, which is equal to $2$."}, "direct_answer": {"text": "Let's think step by step. Let's first calculate $(1-3)/4$. Since $9$ is being divided by $1$, we can use $(1-3)/4$ and $(9-1)/4$. But if we multiply the two, it gives us $2$. So the answer is: $2$.", "value": 0.125}}}, "rollout_id": 9}, {"trace": {"0": {"user_question": "Given a list of conditions, please answer the question. Condition 1: $1/4$; please answer the question. $9$; please answer the question.", "ost_step": {}}, "1": {"subquestion": "What is the value of $9$?", "subanswer": {"text": "$9 = 2$.", "value": 1}, "ost_step": {}, "direct_answer": {"text": "Let's think step by step. The conditions are $1/4$ and $9$. If the first condition is true, then the second condition is false. So, we can ignore the first condition. Then, we have $9 = 2$. Therefore, the answer is: 2.", "value": 0.1875}}}, "rollout_id": 9}, {"trace": {"0": {"user_question": "Given a list of conditions, please answer the question. Condition 1: $1/4$; please answer the question. $9$; please answer the question.", "ost_step": {}}, "1": {"subquestion": "What is the value of $9$?", "subanswer": {"text": "$9 = 2$.", "value": 1}, "ost_step": {}}, "2": {"subquestion": "Now we can answer the question: $9$; please answer the question. $1$.", "subanswer": {"text": "$1 = 1$.", "value": 0.625}, "ost_step": {}}}, "rollout_id": 9}, {"trace": {"0": {"user_question": "Given a list of conditions, please answer the question. Condition 1: $1/4$; please answer the question. $9$; please answer the question.", "ost_step": {}}, "1": {"subquestion": "What is the value of $9$?", "subanswer": {"text": "$9 = 2$.", "value": 1}, "ost_step": {}}, "2": {"subquestion": "Now we can answer the question: What is the value of $1/4$?", "subanswer": {"text": "$1/4 = 0.25$.", "value": 0.75}, "ost_step": {}}}, "rollout_id": 9}]